{
  "word_analysis": [
    {
      "word": "السَّلَامُ)،",
      "pos": "N",
      "translation": {
        "en": "upon him),",
        "ur": "السلام)،",
        "tr": "selam),",
        "fa": "السلام)،",
        "id": "alaihis salam),",
        "bn": "আস-সালাম),",
        "es": "con él),",
        "fr": "soit sur lui),",
        "de": "auf ihm),",
        "ru": "ему),",
        "zh": "平安),"
      }
    },
    {
      "word": "وَأَوْصَى",
      "pos": "V",
      "translation": {
        "en": "and he deputed",
        "ur": "اور وصیت کی",
        "tr": "ve vasiyet etti",
        "fa": "و وصیت کرد",
        "id": "dan berwasiat",
        "bn": "এবং অসিয়ত করলেন",
        "es": "y legó",
        "fr": "et légua",
        "de": "und vermachte",
        "ru": "и завещал",
        "zh": "并嘱托了"
      }
    },
    {
      "word": "إِبْرَاهِيمُ",
      "pos": "N",
      "translation": {
        "en": "Ibrahim",
        "ur": "ابراہیم نے",
        "tr": "İbrahim",
        "fa": "ابراهیم",
        "id": "Ibrahim",
        "bn": "ইব্রাহীম",
        "es": "Abraham",
        "fr": "Abraham",
        "de": "Abraham",
        "ru": "Ибрахим",
        "zh": "易卜拉欣"
      }
    },
    {
      "word": "إِلَى",
      "pos": "PREP",
      "translation": {
        "en": "to",
        "ur": "کی طرف",
        "tr": "-e/-a",
        "fa": "به",
        "id": "kepada",
        "bn": "প্রতি",
        "es": "a",
        "fr": "à",
        "de": "zu",
        "ru": "к",
        "zh": "到"
      }
    },
    {
      "word": "ابْنِهِ",
      "pos": "N",
      "translation": {
        "en": "his son",
        "ur": "اس کے بیٹے",
        "tr": "oğluna",
        "fa": "پسرش",
        "id": "putranya",
        "bn": "তাঁর পুত্র",
        "es": "su hijo",
        "fr": "son fils",
        "de": "seinen Sohn",
        "ru": "своему сыну",
        "zh": "他的儿子"
      }
    },
    {
      "word": "إِسْمَاعِيلَ،",
      "pos": "N",
      "translation": {
        "en": "Isma'il,",
        "ur": "اسماعیل کو،",
        "tr": "İsmail'e,",
        "fa": "اسماعیل،",
        "id": "Isma'il,",
        "bn": "ইসমাঈল,",
        "es": "Isma'il,",
        "fr": "Isma'il,",
        "de": "Isma'il,",
        "ru": "Исмаилу,",
        "zh": "伊斯玛仪,"
      }
    },
    {
      "word": "وَأَوْصَى",
      "pos": "V",
      "translation": {
        "en": "and he deputed",
        "ur": "اور وصیت کی",
        "tr": "ve vasiyet etti",
        "fa": "و وصیت کرد",
        "id": "dan berwasiat",
        "bn": "এবং অসিয়ত করলেন",
        "es": "y legó",
        "fr": "et légua",
        "de": "und vermachte",
        "ru": "и завещал",
        "zh": "并嘱托了"
      }
    },
    {
      "word": "إِسْمَاعِيلُ",
      "pos": "N",
      "translation": {
        "en": "Isma'il",
        "ur": "اسماعیل نے",
        "tr": "İsmail",
        "fa": "اسماعیل",
        "id": "Isma'il",
        "bn": "ইসমাঈল",
        "es": "Isma'il",
        "fr": "Isma'il",
        "de": "Isma'il",
        "ru": "Исмаил",
        "zh": "伊斯玛仪"
      }
    },
    {
      "word": "إِلَى",
      "pos": "PREP",
      "translation": {
        "en": "to",
        "ur": "کی طرف",
        "tr": "-e/-a",
        "fa": "به",
        "id": "kepada",
        "bn": "প্রতি",
        "es": "a",
        "fr": "à",
        "de": "zu",
        "ru": "к",
        "zh": "到"
      }
    },
    {
      "word": "إِسْحَاقَ،",
      "pos": "N",
      "translation": {
        "en": "Ishaq,",
        "ur": "اسحاق کو،",
        "tr": "İshak'a,",
        "fa": "اسحاق،",
        "id": "Ishak,",
        "bn": "ইসহাক,",
        "es": "Isaac,",
        "fr": "Isaac,",
        "de": "Isaak,",
        "ru": "Исхаку,",
        "zh": "伊斯哈格,"
      }
    },
    {
      "word": "وَأَوْصَى",
      "pos": "V",
      "translation": {
        "en": "and he deputed",
        "ur": "اور وصیت کی",
        "tr": "ve vasiyet etti",
        "fa": "و وصیت کرد",
        "id": "dan berwasiat",
        "bn": "এবং অসিয়ত করলেন",
        "es": "y legó",
        "fr": "et légua",
        "de": "und vermachte",
        "ru": "и завещал",
        "zh": "并嘱托了"
      }
    },
    {
      "word": "إِسْحَاقُ",
      "pos": "N",
      "translation": {
        "en": "Ishaq",
        "ur": "اسحاق نے",
        "tr": "İshak",
        "fa": "اسحاق",
        "id": "Ishak",
        "bn": "ইসহাক",
        "es": "Isaac",
        "fr": "Isaac",
        "de": "Isaak",
        "ru": "Исхак",
        "zh": "伊斯哈格"
      }
    },
    {
      "word": "إِلَى",
      "pos": "PREP",
      "translation": {
        "en": "to",
        "ur": "کی طرف",
        "tr": "-e/-a",
        "fa": "به",
        "id": "kepada",
        "bn": "প্রতি",
        "es": "a",
        "fr": "à",
        "de": "zu",
        "ru": "к",
        "zh": "到"
      }
    },
    {
      "word": "يَعْقُوبَ،",
      "pos": "N",
      "translation": {
        "en": "Ya'qub,",
        "ur": "یعقوب کو،",
        "tr": "Yakûb'a,",
        "fa": "یعقوب،",
        "id": "Ya'qub,",
        "bn": "ইয়াকুব,",
        "es": "Jacob,",
        "fr": "Jacob,",
        "de": "Jakob,",
        "ru": "Якубу,",
        "zh": "叶尔孤白,"
      }
    },
    {
      "word": "وَأَوْصَى",
      "pos": "V",
      "translation": {
        "en": "and he deputed",
        "ur": "اور وصیت کی",
        "tr": "ve vasiyet etti",
        "fa": "و وصیت کرد",
        "id": "dan berwasiat",
        "bn": "এবং অসিয়ত করলেন",
        "es": "y legó",
        "fr": "et légua",
        "de": "und vermachte",
        "ru": "и завещал",
        "zh": "并嘱托了"
      }
    },
    {
      "word": "يَعْقُوبُ",
      "pos": "N",
      "translation": {
        "en": "Ya'qub",
        "ur": "یعقوب نے",
        "tr": "Yakûb",
        "fa": "یعقوب",
        "id": "Ya'qub",
        "bn": "ইয়াকুব",
        "es": "Jacob",
        "fr": "Jacob",
        "de": "Jakob",
        "ru": "Якуб",
        "zh": "叶尔孤白"
      }
    },
    {
      "word": "إِلَى",
      "pos": "PREP",
      "translation": {
        "en": "to",
        "ur": "کی طرف",
        "tr": "-e/-a",
        "fa": "به",
        "id": "kepada",
        "bn": "প্রতি",
        "es": "a",
        "fr": "à",
        "de": "zu",
        "ru": "к",
        "zh": "到"
      }
    },
    {
      "word": "يُوسُفَ،",
      "pos": "N",
      "translation": {
        "en": "Yusuf,",
        "ur": "یوسف کو،",
        "tr": "Yûsuf'a,",
        "fa": "یوسف،",
        "id": "Yusuf,",
        "bn": "ইউসুফ,",
        "es": "José,",
        "fr": "Joseph,",
        "de": "Joseph,",
        "ru": "Юсуфу,",
        "zh": "优素福,"
      }
    },
    {
      "word": "وَأَوْصَى",
      "pos": "V",
      "translation": {
        "en": "and he deputed",
        "ur": "اور وصیت کی",
        "tr": "ve vasiyet etti",
        "fa": "و وصیت کرد",
        "id": "dan berwasiat",
        "bn": "এবং অসিয়ত করলেন",
        "es": "y legó",
        "fr": "et légua",
        "de": "und vermachte",
        "ru": "и завещал",
        "zh": "并嘱托了"
      }
    },
    {
      "word": "يُوسُفُ",
      "pos": "N",
      "translation": {
        "en": "Yusuf",
        "ur": "یوسف نے",
        "tr": "Yûsuf",
        "fa": "یوسف",
        "id": "Yusuf",
        "bn": "ইউসুফ",
        "es": "José",
        "fr": "Joseph",
        "de": "Joseph",
        "ru": "Юсуф",
        "zh": "优素福"
      }
    },
    {
      "word": "إِلَى",
      "pos": "PREP",
      "translation": {
        "en": "to",
        "ur": "کی طرف",
        "tr": "-e/-a",
        "fa": "به",
        "id": "kepada",
        "bn": "প্রতি",
        "es": "a",
        "fr": "à",
        "de": "zu",
        "ru": "к",
        "zh": "到"
      }
    },
    {
      "word": "بُثْرِيَاءَ",
      "pos": "N",
      "translation": {
        "en": "Buthriya'",
        "ur": "بثریاء کو",
        "tr": "Büsriyâ'ya",
        "fa": "بثریاء",
        "id": "Butsriya'",
        "bn": "বুছরিয়া",
        "es": "Buthriya'",
        "fr": "Bouthriya'",
        "de": "Buthrija'",
        "ru": "Бусрия",
        "zh": "布斯里亚"
      }
    },
    {
      "word": "(7)،",
      "pos": "PART",
      "translation": {
        "en": "(7),",
        "ur": "(7)،",
        "tr": "(7),",
        "fa": "(7)،",
        "id": "(7),",
        "bn": "(৭),",
        "es": "(7),",
        "fr": "(7),",
        "de": "(7),",
        "ru": "(7),",
        "zh": "(7),"
      }
    },
    {
      "word": "وَأَوْصَى",
      "pos": "V",
      "translation": {
        "en": "and he deputed",
        "ur": "اور وصیت کی",
        "tr": "ve vasiyet etti",
        "fa": "و وصیت کرد",
        "id": "dan berwasiat",
        "bn": "এবং অসিয়ত করলেন",
        "es": "y legó",
        "fr": "et légua",
        "de": "und vermachte",
        "ru": "и завещал",
        "zh": "并嘱托了"
      }
    },
    {
      "word": "بُثْرِيَاءُ",
      "pos": "N",
      "translation": {
        "en": "Buthriya'",
        "ur": "بثریاء نے",
        "tr": "Büsriyâ",
        "fa": "بثریاء",
        "id": "Butsriya'",
        "bn": "বুছরিয়া",
        "es": "Buthriya'",
        "fr": "Bouthriya'",
        "de": "Buthrija'",
        "ru": "Бусрия",
        "zh": "布斯里亚"
      }
    },
    {
      "word": "إِلَى",
      "pos": "PREP",
      "translation": {
        "en": "to",
        "ur": "کی طرف",
        "tr": "-e/-a",
        "fa": "به",
        "id": "kepada",
        "bn": "প্রতি",
        "es": "a",
        "fr": "à",
        "de": "zu",
        "ru": "к",
        "zh": "到"
      }
    },
    {
      "word": "شُعَيْبٍ",
      "pos": "N",
      "translation": {
        "en": "Shu'ayb",
        "ur": "شعیب",
        "tr": "Şuayb",
        "fa": "شعیب",
        "id": "Syu'aib",
        "bn": "শুআইব",
        "es": "Shu'ayb",
        "fr": "Chou'ayb",
        "de": "Schu'aib",
        "ru": "Шуайбу",
        "zh": "舒艾卜"
      }
    },
    {
      "word": "(عَلَيْهِ",
      "pos": "PART",
      "translation": {
        "en": "(peace be",
        "ur": "(علیہ",
        "tr": "(a.s.",
        "fa": "(علیه",
        "id": "(a.s.",
        "bn": "(আলাইহি",
        "es": "(la paz sea",
        "fr": "(que la paix",
        "de": "(Friede sei",
        "ru": "(мир",
        "zh": "(愿他"
      }
    },
    {
      "word": "السَّلَامُ)،",
      "pos": "N",
      "translation": {
        "en": "upon him),",
        "ur": "السلام)،",
        "tr": "selam),",
        "fa": "السلام)،",
        "id": "alaihis salam),",
        "bn": "আস-সালাম),",
        "es": "con él),",
        "fr": "soit sur lui),",
        "de": "auf ihm),",
        "ru": "ему),",
        "zh": "平安),"
      }
    },
    {
      "word": "وَدَفَعَهَا",
      "pos": "V",
      "translation": {
        "en": "and he gave it",
        "ur": "اور اسے دے دیا",
        "tr": "ve onu verdi",
        "fa": "و آن را سپرد",
        "id": "dan menyerahkannya",
        "bn": "এবং তা দিলেন",
        "es": "y la entregó",
        "fr": "et il la remit",
        "de": "und er gab es",
        "ru": "и передал это",
        "zh": "并交付了"
      }
    },
    {
      "word": "شُعَيْبٌ",
      "pos": "N",
      "translation": {
        "en": "Shu'ayb",
        "ur": "شعیب نے",
        "tr": "Şuayb",
        "fa": "شعیب",
        "id": "Syu'aib",
        "bn": "শুআইব",
        "es": "Shu'ayb",
        "fr": "Chou'ayb",
        "de": "Schu'aib",
        "ru": "Шуайб",
        "zh": "舒艾卜"
      }
    },
    {
      "word": "إِلَى",
      "pos": "PREP",
      "translation": {
        "en": "to",
        "ur": "کی طرف",
        "tr": "-e/-a",
        "fa": "به",
        "id": "kepada",
        "bn": "প্রতি",
        "es": "a",
        "fr": "à",
        "de": "zu",
        "ru": "к",
        "zh": "到"
      }
    },
    {
      "word": "مُوسَى",
      "pos": "N",
      "translation": {
        "en": "Musa",
        "ur": "موسیٰ",
        "tr": "Mûsâ",
        "fa": "موسی",
        "id": "Musa",
        "bn": "মুসা",
        "es": "Moisés",
        "fr": "Moïse",
        "de": "Moses",
        "ru": "Мусе",
        "zh": "穆萨"
      }
    },
    {
      "word": "بْنِ",
      "pos": "N",
      "translation": {
        "en": "son of",
        "ur": "بن",
        "tr": "bin",
        "fa": "بن",
        "id": "bin",
        "bn": "ইবনে",
        "es": "hijo de",
        "fr": "fils de",
        "de": "Sohn von",
        "ru": "ибн",
        "zh": "之子"
      }
    },
    {
      "word": "عِمْرَانَ",
      "pos": "N",
      "translation": {
        "en": "'Imran",
        "ur": "عمران",
        "tr": "İmrân",
        "fa": "عمران",
        "id": "'Imran",
        "bn": "ইমরান",
        "es": "'Imran",
        "fr": "'Imran",
        "de": "'Imran",
        "ru": "Имрана",
        "zh": "伊姆兰"
      }
    },
    {
      "word": "(عَلَيْهِ",
      "pos": "PART",
      "translation": {
        "en": "(peace be",
        "ur": "(علیہ",
        "tr": "(a.s.",
        "fa": "(علیه",
        "id": "(a.s.",
        "bn": "(আলাইহি",
        "es": "(la paz sea",
        "fr": "(que la paix",
        "de": "(Friede sei",
        "ru": "(мир",
        "zh": "(愿他"
      }
    },
    {
      "word": "السَّلَامُ)،",
      "pos": "N",
      "translation": {
        "en": "upon him),",
        "ur": "السلام)،",
        "tr": "selam),",
        "fa": "السلام)،",
        "id": "alaihis salam),",
        "bn": "আস-সালাম),",
        "es": "con él),",
        "fr": "soit sur lui),",
        "de": "auf ihm),",
        "ru": "ему),",
        "zh": "平安),"
      }
    },
    {
      "word": "وَأَوْصَى",
      "pos": "V",
      "translation": {
        "en": "and he deputed",
        "ur": "اور وصیت کی",
        "tr": "ve vasiyet etti",
        "fa": "و وصیت کرد",
        "id": "dan berwasiat",
        "bn": "এবং অসিয়ত করলেন",
        "es": "y legó",
        "fr": "et légua",
        "de": "und vermachte",
        "ru": "и завещал",
        "zh": "并嘱托了"
      }
    },
    {
      "word": "مُوسَى",
      "pos": "N",
      "translation": {
        "en": "Musa",
        "ur": "موسیٰ نے",
        "tr": "Mûsâ",
        "fa": "موسی",
        "id": "Musa",
        "bn": "মুসা",
        "es": "Moisés",
        "fr": "Moïse",
        "de": "Moses",
        "ru": "Муса",
        "zh": "穆萨"
      }
    },
    {
      "word": "بْنِ",
      "pos": "N",
      "translation": {
        "en": "son of",
        "ur": "بن",
        "tr": "bin",
        "fa": "بن",
        "id": "bin",
        "bn": "ইবনে",
        "es": "hijo de",
        "fr": "fils de",
        "de": "Sohn von",
        "ru": "ибн",
        "zh": "之子"
      }
    },
    {
      "word": "عِمْرَانَ",
      "pos": "N",
      "translation": {
        "en": "'Imran",
        "ur": "عمران",
        "tr": "İmrân",
        "fa": "عمران",
        "id": "'Imran",
        "bn": "ইমরান",
        "es": "'Imran",
        "fr": "'Imran",
        "de": "'Imran",
        "ru": "Имран",
        "zh": "伊姆兰"
      }
    },
    {
      "word": "(عَلَيْهِ",
      "pos": "PART",
      "translation": {
        "en": "(peace be",
        "ur": "(علیہ",
        "tr": "(a.s.",
        "fa": "(علیه",
        "id": "(a.s.",
        "bn": "(আলাইহি",
        "es": "(la paz sea",
        "fr": "(que la paix",
        "de": "(Friede sei",
        "ru": "(мир",
        "zh": "(愿他"
      }
    },
    {
      "word": "السَّلَامُ)",
      "pos": "N",
      "translation": {
        "en": "upon him)",
        "ur": "السلام)",
        "tr": "selam)",
        "fa": "السلام)",
        "id": "alaihis salam)",
        "bn": "আস-সালাম)",
        "es": "con él)",
        "fr": "soit sur lui)",
        "de": "auf ihm)",
        "ru": "ему)",
        "zh": "平安)"
      }
    },
    {
      "word": "إِلَى",
      "pos": "PREP",
      "translation": {
        "en": "to",
        "ur": "کی طرف",
        "tr": "-e/-a",
        "fa": "به",
        "id": "kepada",
        "bn": "প্রতি",
        "es": "a",
        "fr": "à",
        "de": "zu",
        "ru": "к",
        "zh": "到"
      }
    },
    {
      "word": "يُوشَعَ",
      "pos": "N",
      "translation": {
        "en": "Yusha'",
        "ur": "یوشع",
        "tr": "Yûşa",
        "fa": "یوشع",
        "id": "Yusya'",
        "bn": "ইউশা",
        "es": "Josué",
        "fr": "Josué",
        "de": "Josua",
        "ru": "Юшы",
        "zh": "约书亚"
      }
    },
    {
      "word": "بْنِ",
      "pos": "N",
      "translation": {
        "en": "son of",
        "ur": "بن",
        "tr": "bin",
        "fa": "بن",
        "id": "bin",
        "bn": "ইবনে",
        "es": "hijo de",
        "fr": "fils de",
        "de": "Sohn von",
        "ru": "ибн",
        "zh": "之子"
      }
    },
    {
      "word": "نُونٍ،",
      "pos": "N",
      "translation": {
        "en": "Nun,",
        "ur": "نون کو،",
        "tr": "Nûn'a,",
        "fa": "نون،",
        "id": "Nun,",
        "bn": "নূন,",
        "es": "Nun,",
        "fr": "Noun,",
        "de": "Nun,",
        "ru": "Нуна,",
        "zh": "努恩,"
      }
    },
    {
      "word": "وَأَوْصَى",
      "pos": "V",
      "translation": {
        "en": "and he deputed",
        "ur": "اور وصیت کی",
        "tr": "ve vasiyet etti",
        "fa": "و وصیت کرد",
        "id": "dan berwasiat",
        "bn": "এবং অসিয়ত করলেন",
        "es": "y legó",
        "fr": "et légua",
        "de": "und vermachte",
        "ru": "и завещал",
        "zh": "并嘱托了"
      }
    },
    {
      "word": "يُوشَعُ",
      "pos": "N",
      "translation": {
        "en": "Yusha'",
        "ur": "یوشع نے",
        "tr": "Yûşa",
        "fa": "یوشع",
        "id": "Yusya'",
        "bn": "ইউশা",
        "es": "Josué",
        "fr": "Josué",
        "de": "Josua",
        "ru": "Юша",
        "zh": "约书亚"
      }
    },
    {
      "word": "بْنِ",
      "pos": "N",
      "translation": {
        "en": "son of",
        "ur": "بن",
        "tr": "bin",
        "fa": "بن",
        "id": "bin",
        "bn": "ইবনে",
        "es": "hijo de",
        "fr": "fils de",
        "de": "Sohn von",
        "ru": "ибн",
        "zh": "之子"
      }
    },
    {
      "word": "نُونٍ",
      "pos": "N",
      "translation": {
        "en": "Nun",
        "ur": "نون",
        "tr": "Nûn",
        "fa": "نون",
        "id": "Nun",
        "bn": "নূন",
        "es": "Nun",
        "fr": "Noun",
        "de": "Nun",
        "ru": "Нун",
        "zh": "努恩"
      }
    },
    {
      "word": "إِلَى",
      "pos": "PREP",
      "translation": {
        "en": "to",
        "ur": "کی طرف",
        "tr": "-e/-a",
        "fa": "به",
        "id": "kepada",
        "bn": "প্রতি",
        "es": "a",
        "fr": "à",
        "de": "zu",
        "ru": "к",
        "zh": "到"
      }
    },
    {
      "word": "دَاوُدَ",
      "pos": "N",
      "translation": {
        "en": "Dawud",
        "ur": "داؤد",
        "tr": "Dâvud",
        "fa": "داود",
        "id": "Dawud",
        "bn": "দাউদ",
        "es": "David",
        "fr": "David",
        "de": "David",
        "ru": "Давуду",
        "zh": "达乌德"
      }
    },
    {
      "word": "(عَلَيْهِ",
      "pos": "PART",
      "translation": {
        "en": "(peace be",
        "ur": "(علیہ",
        "tr": "(a.s.",
        "fa": "(علیه",
        "id": "(a.s.",
        "bn": "(আলাইহি",
        "es": "(la paz sea",
        "fr": "(que la paix",
        "de": "(Friede sei",
        "ru": "(мир",
        "zh": "(愿他"
      }
    },
    {
      "word": "السَّلَامُ)،",
      "pos": "N",
      "translation": {
        "en": "upon him),",
        "ur": "السلام)،",
        "tr": "selam),",
        "fa": "السلام)،",
        "id": "alaihis salam),",
        "bn": "আস-সালাম),",
        "es": "con él),",
        "fr": "soit sur lui),",
        "de": "auf ihm),",
        "ru": "ему),",
        "zh": "平安),"
      }
    },
    {
      "word": "وَأَوْصَى",
      "pos": "V",
      "translation": {
        "en": "and he deputed",
        "ur": "اور وصیت کی",
        "tr": "ve vasiyet etti",
        "fa": "و وصیت کرد",
        "id": "dan berwasiat",
        "bn": "এবং অসিয়ত করলেন",
        "es": "y legó",
        "fr": "et légua",
        "de": "und vermachte",
        "ru": "и завещал",
        "zh": "并嘱托了"
      }
    },
    {
      "word": "دَاوُدُ",
      "pos": "N",
      "translation": {
        "en": "Dawud",
        "ur": "داؤد نے",
        "tr": "Dâvud",
        "fa": "داود",
        "id": "Dawud",
        "bn": "দাউদ",
        "es": "David",
        "fr": "David",
        "de": "David",
        "ru": "Давуд",
        "zh": "达乌德"
      }
    },
    {
      "word": "(عَلَيْهِ",
      "pos": "PART",
      "translation": {
        "en": "(peace be",
        "ur": "(علیہ",
        "tr": "(a.s.",
        "fa": "(علیه",
        "id": "(a.s.",
        "bn": "(আলাইহি",
        "es": "(la paz sea",
        "fr": "(que la paix",
        "de": "(Friede sei",
        "ru": "(мир",
        "zh": "(愿他"
      }
    },
    {
      "word": "السَّلَامُ)",
      "pos": "N",
      "translation": {
        "en": "upon him)",
        "ur": "السلام)",
        "tr": "selam)",
        "fa": "السلام)",
        "id": "alaihis salam)",
        "bn": "আস-সালাম)",
        "es": "con él)",
        "fr": "soit sur lui)",
        "de": "auf ihm)",
        "ru": "ему)",
        "zh": "平安)"
      }
    },
    {
      "word": "إِلَى",
      "pos": "PREP",
      "translation": {
        "en": "to",
        "ur": "کی طرف",
        "tr": "-e/-a",
        "fa": "به",
        "id": "kepada",
        "bn": "প্রতি",
        "es": "a",
        "fr": "à",
        "de": "zu",
        "ru": "к",
        "zh": "到"
      }
    },
    {
      "word": "سُلَيْمَانَ",
      "pos": "N",
      "translation": {
        "en": "Sulayman",
        "ur": "سلیمان",
        "tr": "Süleyman",
        "fa": "سلیمان",
        "id": "Sulaiman",
        "bn": "সুলাইমান",
        "es": "Salomón",
        "fr": "Salomon",
        "de": "Salomon",
        "ru": "Сулейману",
        "zh": "苏莱曼"
      }
    },
    {
      "word": "(عَلَيْهِ",
      "pos": "PART",
      "translation": {
        "en": "(peace be",
        "ur": "(علیہ",
        "tr": "(a.s.",
        "fa": "(علیه",
        "id": "(a.s.",
        "bn": "(আলাইহি",
        "es": "(la paz sea",
        "fr": "(que la paix",
        "de": "(Friede sei",
        "ru": "(мир",
        "zh": "(愿他"
      }
    },
    {
      "word": "السَّلَامُ)،",
      "pos": "N",
      "translation": {
        "en": "upon him),",
        "ur": "السلام)،",
        "tr": "selam),",
        "fa": "السلام)،",
        "id": "alaihis salam),",
        "bn": "আস-সালাম),",
        "es": "con él),",
        "fr": "soit sur lui),",
        "de": "auf ihm),",
        "ru": "ему),",
        "zh": "平安),"
      }
    },
    {
      "word": "وَأَوْصَى",
      "pos": "V",
      "translation": {
        "en": "and he deputed",
        "ur": "اور وصیت کی",
        "tr": "ve vasiyet etti",
        "fa": "و وصیت کرد",
        "id": "dan berwasiat",
        "bn": "এবং অসিয়ত করলেন",
        "es": "y legó",
        "fr": "et légua",
        "de": "und vermachte",
        "ru": "и завещал",
        "zh": "并嘱托了"
      }
    },
    {
      "word": "سُلَيْمَانُ",
      "pos": "N",
      "translation": {
        "en": "Sulayman",
        "ur": "سلیمان نے",
        "tr": "Süleyman",
        "fa": "سلیمان",
        "id": "Sulaiman",
        "bn": "সুলাইমান",
        "es": "Salomón",
        "fr": "Salomon",
        "de": "Salomon",
        "ru": "Сулейман",
        "zh": "苏莱曼"
      }
    },
    {
      "word": "(عَلَيْهِ",
      "pos": "PART",
      "translation": {
        "en": "(peace be",
        "ur": "(علیہ",
        "tr": "(a.s.",
        "fa": "(علیه",
        "id": "(a.s.",
        "bn": "(আলাইহি",
        "es": "(la paz sea",
        "fr": "(que la paix",
        "de": "(Friede sei",
        "ru": "(мир",
        "zh": "(愿他"
      }
    },
    {
      "word": "السَّلَامُ)",
      "pos": "N",
      "translation": {
        "en": "upon him)",
        "ur": "السلام)",
        "tr": "selam)",
        "fa": "السلام)",
        "id": "alaihis salam)",
        "bn": "আস-সালাম)",
        "es": "con él)",
        "fr": "soit sur lui)",
        "de": "auf ihm)",
        "ru": "ему)",
        "zh": "平安)"
      }
    },
    {
      "word": "إِلَى",
      "pos": "PREP",
      "translation": {
        "en": "to",
        "ur": "کی طرف",
        "tr": "-e/-a",
        "fa": "به",
        "id": "kepada",
        "bn": "প্রতি",
        "es": "a",
        "fr": "à",
        "de": "zu",
        "ru": "к",
        "zh": "到"
      }
    },
    {
      "word": "آصَفَ",
      "pos": "N",
      "translation": {
        "en": "Asif",
        "ur": "آصف",
        "tr": "Âsıf",
        "fa": "آصف",
        "id": "Ashif",
        "bn": "আসিফ",
        "es": "Asif",
        "fr": "Assif",
        "de": "Asif",
        "ru": "Асифу",
        "zh": "阿西夫"
      }
    },
    {
      "word": "بْنِ",
      "pos": "N",
      "translation": {
        "en": "son of",
        "ur": "بن",
        "tr": "bin",
        "fa": "بن",
        "id": "bin",
        "bn": "ইবনে",
        "es": "hijo de",
        "fr": "fils de",
        "de": "Sohn von",
        "ru": "ибн",
        "zh": "之子"
      }
    },
    {
      "word": "بَرْخِيَا،",
      "pos": "N",
      "translation": {
        "en": "Barkhiyya,",
        "ur": "برخیا کو،",
        "tr": "Berhiyâ'ya,",
        "fa": "برخیا،",
        "id": "Barkhiyya,",
        "bn": "বারখিয়্যা,",
        "es": "Barkhiyya,",
        "fr": "Barkhiyya,",
        "de": "Barchija,",
        "ru": "Бархию,",
        "zh": "巴尔希亚,"
      }
    },
    {
      "word": "وَأَوْصَى",
      "pos": "V",
      "translation": {
        "en": "and he deputed",
        "ur": "اور وصیت کی",
        "tr": "ve vasiyet etti",
        "fa": "و وصیت کرد",
        "id": "dan berwasiat",
        "bn": "এবং অসিয়ত করলেন",
        "es": "y legó",
        "fr": "et légua",
        "de": "und vermachte",
        "ru": "и завещал",
        "zh": "并嘱托了"
      }
    },
    {
      "word": "آصَفُ",
      "pos": "N",
      "translation": {
        "en": "Asif",
        "ur": "آصف نے",
        "tr": "Âsıf",
        "fa": "آصف",
        "id": "Ashif",
        "bn": "আসিফ",
        "es": "Asif",
        "fr": "Assif",
        "de": "Asif",
        "ru": "Асиф",
        "zh": "阿西夫"
      }
    },
    {
      "word": "بْنِ",
      "pos": "N",
      "translation": {
        "en": "son of",
        "ur": "بن",
        "tr": "bin",
        "fa": "بن",
        "id": "bin",
        "bn": "ইবনে",
        "es": "hijo de",
        "fr": "fils de",
        "de": "Sohn von",
        "ru": "ибн",
        "zh": "之子"
      }
    },
    {
      "word": "بَرْخِيَا",
      "pos": "N",
      "translation": {
        "en": "Barkhiyya",
        "ur": "برخیا",
        "tr": "Berhiyâ",
        "fa": "برخیا",
        "id": "Barkhiyya",
        "bn": "বারখিয়্যা",
        "es": "Barkhiyya",
        "fr": "Barkhiyya",
        "de": "Barchija",
        "ru": "Бархия",
        "zh": "巴尔希亚"
      }
    },
    {
      "word": "إِلَى",
      "pos": "PREP",
      "translation": {
        "en": "to",
        "ur": "کی طرف",
        "tr": "-e/-a",
        "fa": "به",
        "id": "kepada",
        "bn": "প্রতি",
        "es": "a",
        "fr": "à",
        "de": "zu",
        "ru": "к",
        "zh": "到"
      }
    },
    {
      "word": "زَكَرِيَّا",
      "pos": "N",
      "translation": {
        "en": "Zakariyya",
        "ur": "زکریا",
        "tr": "Zekeriya",
        "fa": "زکریا",
        "id": "Zakariyya",
        "bn": "যাকারিয়্যা",
        "es": "Zacarías",
        "fr": "Zacharie",
        "de": "Zacharias",
        "ru": "Закарийе",
        "zh": "宰凯里亚"
      }
    },
    {
      "word": "(عَلَيْهِ",
      "pos": "PART",
      "translation": {
        "en": "(peace be",
        "ur": "(علیہ",
        "tr": "(a.s.",
        "fa": "(علیه",
        "id": "(a.s.",
        "bn": "(আলাইহি",
        "es": "(la paz sea",
        "fr": "(que la paix",
        "de": "(Friede sei",
        "ru": "(мир",
        "zh": "(愿他"
      }
    },
    {
      "word": "السَّلَامُ)،",
      "pos": "N",
      "translation": {
        "en": "upon him),",
        "ur": "السلام)،",
        "tr": "selam),",
        "fa": "السلام)،",
        "id": "alaihis salam),",
        "bn": "আস-সালাম),",
        "es": "con él),",
        "fr": "soit sur lui),",
        "de": "auf ihm),",
        "ru": "ему),",
        "zh": "平安),"
      }
    },
    {
      "word": "وَدَفَعَهَا",
      "pos": "V",
      "translation": {
        "en": "and he gave it",
        "ur": "اور اسے دے دیا",
        "tr": "ve onu verdi",
        "fa": "و آن را سپرد",
        "id": "dan menyerahkannya",
        "bn": "এবং তা দিলেন",
        "es": "y la entregó",
        "fr": "et il la remit",
        "de": "und er gab es",
        "ru": "и передал это",
        "zh": "并交付了"
      }
    },
    {
      "word": "زَكَرِيَّا",
      "pos": "N",
      "translation": {
        "en": "Zakariyya",
        "ur": "زکریا نے",
        "tr": "Zekeriya",
        "fa": "زکریا",
        "id": "Zakariyya",
        "bn": "যাকারিয়্যা",
        "es": "Zacarías",
        "fr": "Zacharie",
        "de": "Zacharias",
        "ru": "Закария",
        "zh": "宰凯里亚"
      }
    },
    {
      "word": "(عَلَيْهِ",
      "pos": "PART",
      "translation": {
        "en": "(peace be",
        "ur": "(علیہ",
        "tr": "(a.s.",
        "fa": "(علیه",
        "id": "(a.s.",
        "bn": "(আলাইহি",
        "es": "(la paz sea",
        "fr": "(que la paix",
        "de": "(Friede sei",
        "ru": "(мир",
        "zh": "(愿他"
      }
    },
    {
      "word": "السَّلَامُ)",
      "pos": "N",
      "translation": {
        "en": "upon him)",
        "ur": "السلام)",
        "tr": "selam)",
        "fa": "السلام)",
        "id": "alaihis salam)",
        "bn": "আস-সালাম)",
        "es": "con él)",
        "fr": "soit sur lui)",
        "de": "auf ihm)",
        "ru": "ему)",
        "zh": "平安)"
      }
    },
    {
      "word": "إِلَى",
      "pos": "PREP",
      "translation": {
        "en": "to",
        "ur": "کی طرف",
        "tr": "-e/-a",
        "fa": "به",
        "id": "kepada",
        "bn": "প্রতি",
        "es": "a",
        "fr": "à",
        "de": "zu",
        "ru": "к",
        "zh": "到"
      }
    },
    {
      "word": "عِيسَى",
      "pos": "N",
      "translation": {
        "en": "'Isa",
        "ur": "عیسیٰ",
        "tr": "Îsâ",
        "fa": "عیسی",
        "id": "'Isa",
        "bn": "ঈসা",
        "es": "Jesús",
        "fr": "Jésus",
        "de": "Jesus",
        "ru": "Исе",
        "zh": "尔萨"
      }
    },
    {
      "word": "بْنِ",
      "pos": "N",
      "translation": {
        "en": "son of",
        "ur": "بن",
        "tr": "bin",
        "fa": "بن",
        "id": "bin",
        "bn": "ইবনে",
        "es": "hijo de",
        "fr": "fils de",
        "de": "Sohn von",
        "ru": "ибн",
        "zh": "之子"
      }
    },
    {
      "word": "مَرْيَمَ",
      "pos": "N",
      "translation": {
        "en": "Maryam",
        "ur": "مریم",
        "tr": "Meryem",
        "fa": "مریم",
        "id": "Maryam",
        "bn": "মারিয়াম",
        "es": "María",
        "fr": "Marie",
        "de": "Maria",
        "ru": "Марьям",
        "zh": "麦尔彦"
      }
    },
    {
      "word": "(عَلَيْهِ",
      "pos": "PART",
      "translation": {
        "en": "(peace be",
        "ur": "(علیہ",
        "tr": "(a.s.",
        "fa": "(علیه",
        "id": "(a.s.",
        "bn": "(আলাইহি",
        "es": "(la paz sea",
        "fr": "(que la paix",
        "de": "(Friede sei",
        "ru": "(мир",
        "zh": "(愿他"
      }
    },
    {
      "word": "السَّلَامُ)،",
      "pos": "N",
      "translation": {
        "en": "upon him),",
        "ur": "السلام)،",
        "tr": "selam),",
        "fa": "السلام)،",
        "id": "alaihis salam),",
        "bn": "আস-সালাম),",
        "es": "con él),",
        "fr": "soit sur lui),",
        "de": "auf ihm),",
        "ru": "ему),",
        "zh": "平安),"
      }
    },
    {
      "word": "وَأَوْصَى",
      "pos": "V",
      "translation": {
        "en": "and he deputed",
        "ur": "اور وصیت کی",
        "tr": "ve vasiyet etti",
        "fa": "و وصیت کرد",
        "id": "dan berwasiat",
        "bn": "এবং অসিয়ত করলেন",
        "es": "y legó",
        "fr": "et légua",
        "de": "und vermachte",
        "ru": "и завещал",
        "zh": "并嘱托了"
      }
    },
    {
      "word": "عِيسَى",
      "pos": "N",
      "translation": {
        "en": "'Isa",
        "ur": "عیسیٰ نے",
        "tr": "Îsâ",
        "fa": "عیسی",
        "id": "'Isa",
        "bn": "ঈসা",
        "es": "Jesús",
        "fr": "Jésus",
        "de": "Jesus",
        "ru": "Иса",
        "zh": "尔萨"
      }
    },
    {
      "word": "إِلَى",
      "pos": "PREP",
      "translation": {
        "en": "to",
        "ur": "کی طرف",
        "tr": "-e/-a",
        "fa": "به",
        "id": "kepada",
        "bn": "প্রতি",
        "es": "a",
        "fr": "à",
        "de": "zu",
        "ru": "к",
        "zh": "到"
      }
    },
    {
      "word": "شَمْعُونَ",
      "pos": "N",
      "translation": {
        "en": "Sham'un",
        "ur": "شمعون",
        "tr": "Şem'ûn",
        "fa": "شمعون",
        "id": "Syam'un",
        "bn": "শামউন",
        "es": "Simón",
        "fr": "Simon",
        "de": "Simeon",
        "ru": "Шамуну",
        "zh": "舍蒙"
      }
    },
    {
      "word": "بْنِ",
      "pos": "N",
      "translation": {
        "en": "son of",
        "ur": "بن",
        "tr": "bin",
        "fa": "بن",
        "id": "bin",
        "bn": "ইবনে",
        "es": "hijo de",
        "fr": "fils de",
        "de": "Sohn von",
        "ru": "ибн",
        "zh": "之子"
      }
    },
    {
      "word": "حَمُّونَ",
      "pos": "N",
      "translation": {
        "en": "Hammun",
        "ur": "حمون",
        "tr": "Ham'ûn",
        "fa": "حمون",
        "id": "Hammun",
        "bn": "হাম্মুন",
        "es": "Hammun",
        "fr": "Ham'oun",
        "de": "Hammun",
        "ru": "Хаммуна",
        "zh": "哈蒙"
      }
    },
    {
      "word": "الصَّفَا،",
      "pos": "N",
      "translation": {
        "en": "al-Safa,",
        "ur": "الصفاء،",
        "tr": "es-Safâ,",
        "fa": "صفا،",
        "id": "al-Shafa,",
        "bn": "আস-সাফা,",
        "es": "al-Safa,",
        "fr": "al-Safa,",
        "de": "al-Safa,",
        "ru": "ас-Сафа,",
        "zh": "萨法,"
      }
    },
    {
      "word": "وَأَوْصَى",
      "pos": "V",
      "translation": {
        "en": "and he deputed",
        "ur": "اور وصیت کی",
        "tr": "ve vasiyet etti",
        "fa": "و وصیت کرد",
        "id": "dan berwasiat",
        "bn": "এবং অসিয়ত করলেন",
        "es": "y legó",
        "fr": "et légua",
        "de": "und vermachte",
        "ru": "и завещал",
        "zh": "并嘱托了"
      }
    },
    {
      "word": "شَمْعُونُ",
      "pos": "N",
      "translation": {
        "en": "Sham'un",
        "ur": "شمعون نے",
        "tr": "Şem'ûn",
        "fa": "شمعون",
        "id": "Syam'un",
        "bn": "শামউন",
        "es": "Simón",
        "fr": "Simon",
        "de": "Simeon",
        "ru": "Шамун",
        "zh": "舍蒙"
      }
    },
    {
      "word": "إِلَى",
      "pos": "PREP",
      "translation": {
        "en": "to",
        "ur": "کی طرف",
        "tr": "-e/-a",
        "fa": "به",
        "id": "kepada",
        "bn": "প্রতি",
        "es": "a",
        "fr": "à",
        "de": "zu",
        "ru": "к",
        "zh": "到"
      }
    },
    {
      "word": "يَحْيَى",
      "pos": "N",
      "translation": {
        "en": "Yahya",
        "ur": "یحییٰ",
        "tr": "Yahyâ",
        "fa": "یحیی",
        "id": "Yahya",
        "bn": "ইয়াহইয়া",
        "es": "Juan",
        "fr": "Jean",
        "de": "Johannes",
        "ru": "Яхье",
        "zh": "叶哈雅"
      }
    },
    {
      "word": "بْنِ",
      "pos": "N",
      "translation": {
        "en": "son of",
        "ur": "بن",
        "tr": "bin",
        "fa": "بن",
        "id": "bin",
        "bn": "ইবনে",
        "es": "hijo de",
        "fr": "fils de",
        "de": "Sohn von",
        "ru": "ибн",
        "zh": "之子"
      }
    },
    {
      "word": "زَكَرِيَّا،",
      "pos": "N",
      "translation": {
        "en": "Zakariyya,",
        "ur": "زکریا کو،",
        "tr": "Zekeriya'ya,",
        "fa": "زکریا،",
        "id": "Zakariyya,",
        "bn": "যাকারিয়্যা,",
        "es": "Zacarías,",
        "fr": "Zacharie,",
        "de": "Zacharias,",
        "ru": "Закарии,",
        "zh": "宰凯里亚,"
      }
    },
    {
      "word": "وَأَوْصَى",
      "pos": "V",
      "translation": {
        "en": "and he deputed",
        "ur": "اور وصیت کی",
        "tr": "ve vasiyet etti",
        "fa": "و وصیت کرد",
        "id": "dan berwasiat",
        "bn": "এবং অসিয়ত করলেন",
        "es": "y legó",
        "fr": "et légua",
        "de": "und vermachte",
        "ru": "и завещал",
        "zh": "并嘱托了"
      }
    },
    {
      "word": "يَحْيَى",
      "pos": "N",
      "translation": {
        "en": "Yahya",
        "ur": "یحییٰ نے",
        "tr": "Yahyâ",
        "fa": "یحیی",
        "id": "Yahya",
        "bn": "ইয়াহইয়া",
        "es": "Juan",
        "fr": "Jean",
        "de": "Johannes",
        "ru": "Яхья",
        "zh": "叶哈雅"
      }
    },
    {
      "word": "بْنِ",
      "pos": "N",
      "translation": {
        "en": "son of",
        "ur": "بن",
        "tr": "bin",
        "fa": "بن",
        "id": "bin",
        "bn": "ইবনে",
        "es": "hijo de",
        "fr": "fils de",
        "de": "Sohn von",
        "ru": "ибн",
        "zh": "之子"
      }
    },
    {
      "word": "زَكَرِيَّا",
      "pos": "N",
      "translation": {
        "en": "Zakariyya",
        "ur": "زکریا",
        "tr": "Zekeriya",
        "fa": "زکریا",
        "id": "Zakariyya",
        "bn": "যাকারিয়্যা",
        "es": "Zacarías",
        "fr": "Zacharie",
        "de": "Zacharias",
        "ru": "Закарии",
        "zh": "宰凯里亚"
      }
    },
    {
      "word": "إِلَى",
      "pos": "PREP",
      "translation": {
        "en": "to",
        "ur": "کی طرف",
        "tr": "-e/-a",
        "fa": "به",
        "id": "kepada",
        "bn": "প্রতি",
        "es": "a",
        "fr": "à",
        "de": "zu",
        "ru": "к",
        "zh": "到"
      }
    },
    {
      "word": "مُنْذِرٍ،",
      "pos": "N",
      "translation": {
        "en": "Mundhir,",
        "ur": "منذر کو،",
        "tr": "Münzir'e,",
        "fa": "منذر،",
        "id": "Mundzir,",
        "bn": "মুনযির,",
        "es": "Mundhir,",
        "fr": "Moundhir,",
        "de": "Mundschir,",
        "ru": "Мунзиру,",
        "zh": "蒙齐尔,"
      }
    },
    {
      "word": "وَأَوْصَى",
      "pos": "V",
      "translation": {
        "en": "and he deputed",
        "ur": "اور وصیت کی",
        "tr": "ve vasiyet etti",
        "fa": "و وصیت کرد",
        "id": "dan berwasiat",
        "bn": "এবং অসিয়ত করলেন",
        "es": "y legó",
        "fr": "et légua",
        "de": "und vermachte",
        "ru": "и завещал",
        "zh": "并嘱托了"
      }
    },
    {
      "word": "مُنْذِرُ",
      "pos": "N",
      "translation": {
        "en": "Mundhir",
        "ur": "منذر نے",
        "tr": "Münzir",
        "fa": "منذر",
        "id": "Mundzir",
        "bn": "মুনযির",
        "es": "Mundhir",
        "fr": "Moundhir",
        "de": "Mundschir",
        "ru": "Мунзир",
        "zh": "蒙齐尔"
      }
    },
    {
      "word": "إِلَى",
      "pos": "PREP",
      "translation": {
        "en": "to",
        "ur": "کی طرف",
        "tr": "-e/-a",
        "fa": "به",
        "id": "kepada",
        "bn": "প্রতি",
        "es": "a",
        "fr": "à",
        "de": "zu",
        "ru": "к",
        "zh": "到"
      }
    },
    {
      "word": "سَلِيمَةَ،",
      "pos": "N",
      "translation": {
        "en": "Sulayma,",
        "ur": "سلیمہ کو،",
        "tr": "Selîme'ye,",
        "fa": "سلیمه،",
        "id": "Salimah,",
        "bn": "সালীমাহ,",
        "es": "Sulayma,",
        "fr": "Soulayma,",
        "de": "Sulayma,",
        "ru": "Салиме,",
        "zh": "萨利玛,"
      }
    },
    {
      "word": "وَأَوْصَى",
      "pos": "V",
      "translation": {
        "en": "and he deputed",
        "ur": "اور وصیت کی",
        "tr": "ve vasiyet etti",
        "fa": "و وصیت کرد",
        "id": "dan berwasiat",
        "bn": "এবং অসিয়ত করলেন",
        "es": "y legó",
        "fr": "et légua",
        "de": "und vermachte",
        "ru": "и завещал",
        "zh": "并嘱托了"
      }
    },
    {
      "word": "سَلِيمَةُ",
      "pos": "N",
      "translation": {
        "en": "Sulayma",
        "ur": "سلیمہ نے",
        "tr": "Selîme",
        "fa": "سلیمه",
        "id": "Salimah",
        "bn": "সালীমাহ",
        "es": "Sulayma",
        "fr": "Soulayma",
        "de": "Sulayma",
        "ru": "Салима",
        "zh": "萨利玛"
      }
    },
    {
      "word": "إِلَى",
      "pos": "PREP",
      "translation": {
        "en": "to",
        "ur": "کی طرف",
        "tr": "-e/-a",
        "fa": "به",
        "id": "kepada",
        "bn": "প্রতি",
        "es": "a",
        "fr": "à",
        "de": "zu",
        "ru": "к",
        "zh": "到"
      }
    },
    {
      "word": "بُرْدَةَ.",
      "pos": "N",
      "translation": {
        "en": "Burda.",
        "ur": "بردۃ کو۔",
        "tr": "Bürde'ye.",
        "fa": "بردة.",
        "id": "Burdah.",
        "bn": "বুরদাহ.",
        "es": "Burda.",
        "fr": "Bourda.",
        "de": "Burda.",
        "ru": "Бурде.",
        "zh": "布尔达."
      }
    }
  ],
  "translations": {
    "en": "Ibrahim deputed his son Isma'il. Isma'il deputed Ishaq. Ishaq deputed Ya'qub. Ya'qub deputed Yusuf. Yusuf deputed Buthriya'. Buthriya' deputed Shu'ayb (peace be upon him). Shu'ayb gave it to Musa b. 'Imran (peace be upon him). Musa b. 'Imran (peace be upon him) deputed Yusha' b. Nun. Yusha' b. Nun deputed Dawud (peace be upon him). Dawud (peace be upon him) deputed Sulayman (peace be upon him). Sulayman (peace be upon him) deputed Asif b. Barkhiyya. Asif b. Barkhiyya deputed Zakariyya (peace be upon him). Zakariyya (peace be upon him) gave it to 'Isa b. Maryam (peace be upon him). 'Isa deputed Sham'un b. Hammun al-Safa. Sham'un deputed Yahya b. Zakariyya. Yahya b. Zakariyya deputed Mundhir. Mundhir deputed Sulayma. Sulayma deputed Burda.",
    "ur": "ابراہیم نے اپنے بیٹے اسماعیل کو وصیت کی۔ اسماعیل نے اسحاق کو، اسحاق نے یعقوب کو، یعقوب نے یوسف کو، یوسف نے بثریاء کو، بثریاء نے شعیب کو، شعیب نے موسیٰ بن عمران کو دیا۔ موسیٰ بن عمران نے یوشع بن نون کو، یوشع بن نون نے داؤد کو، داؤد نے سلیمان کو، سلیمان نے آصف بن برخیا کو، آصف بن برخیا نے زکریا کو، زکریا نے عیسیٰ بن مریم کو دیا۔ عیسیٰ نے شمعون بن حمون الصفاء کو، شمعون نے یحییٰ بن زکریا کو، یحییٰ بن زکریا نے منذر کو، منذر نے سلیمہ کو، سلیمہ نے بردۃ کو وصیت کی۔",
    "tr": "İbrahim oğlu İsmail'e vasiyet etti. İsmail İshak'a, İshak Yakûb'a, Yakûb Yûsuf'a, Yûsuf Büsriyâ'ya, Büsriyâ Şuayb'a, Şuayb Mûsâ b. İmrân'a verdi. Mûsâ b. İmrân Yûşa b. Nûn'a, Yûşa b. Nûn Dâvud'a, Dâvud Süleyman'a, Süleyman Âsıf b. Berhiyâ'ya, Âsıf b. Berhiyâ Zekeriya'ya, Zekeriya Îsâ b. Meryem'e verdi. Îsâ Şem'ûn b. Ham'ûn es-Safâ'ya, Şem'ûn Yahyâ b. Zekeriya'ya, Yahyâ b. Zekeriya Münzir'e, Münzir Selîme'ye, Selîme Bürde'ye vasiyet etti.",
    "fa": "ابراهیم به پسرش اسماعیل وصیت کرد. اسماعیل به اسحاق، اسحاق به یعقوب، یعقوب به یوسف، یوسف به بثریاء، بثریاء به شعیب، شعیب به موسی بن عمران سپرد. موسی بن عمران به یوشع بن نون، یوشع بن نون به داود، داود به سلیمان، سلیمان به آصف بن برخیا، آصف بن برخیا به زکریا، زکریا به عیسی بن مریم سپرد. عیسی به شمعون بن حمون صفا، شمعون به یحیی بن زکریا، یحیی بن زکریا به منذر، منذر به سلیمه، سلیمه به بردة وصیت کرد.",
    "id": "Ibrahim berwasiat kepada putranya Isma'il. Isma'il kepada Ishak, Ishak kepada Ya'qub, Ya'qub kepada Yusuf, Yusuf kepada Butsriya', Butsriya' kepada Syu'aib, Syu'aib menyerahkannya kepada Musa bin 'Imran. Musa bin 'Imran kepada Yusya' bin Nun, Yusya' bin Nun kepada Dawud, Dawud kepada Sulaiman, Sulaiman kepada Ashif bin Barkhiyya, Ashif bin Barkhiyya kepada Zakariyya, Zakariyya menyerahkannya kepada 'Isa bin Maryam. 'Isa kepada Syam'un bin Hammun al-Shafa, Syam'un kepada Yahya bin Zakariyya, Yahya bin Zakariyya kepada Mundzir, Mundzir kepada Salimah, Salimah kepada Burdah.",
    "bn": "ইব্রাহীম তাঁর পুত্র ইসমাঈলকে অসিয়ত করলেন। ইসমাঈল ইসহাককে, ইসহাক ইয়াকুবকে, ইয়াকুব ইউসুফকে, ইউসুফ বুছরিয়াকে, বুছরিয়া শুআইবকে, শুআইব মুসা ইবনে ইমরানকে দিলেন। মুসা ইবনে ইমরান ইউশা ইবনে নূনকে, ইউশা ইবনে নূন দাউদকে, দাউদ সুলাইমানকে, সুলাইমান আসিফ ইবনে বারখিয়্যাকে, আসিফ ইবনে বারখিয়্যা যাকারিয়্যাকে, যাকারিয়্যা ঈসা ইবনে মারিয়ামকে দিলেন। ঈসা শামউন ইবনে হাম্মুন আস-সাফাকে, শামউন ইয়াহইয়া ইবনে যাকারিয়্যাকে, ইয়াহইয়া ইবনে যাকারিয়্যা মুনযিরকে, মুনযির সালীমাহকে, সালীমাহ বুরদাহকে অসিয়ত করলেন।",
    "es": "Abraham legó a su hijo Ismael. Ismael a Isaac, Isaac a Jacob, Jacob a José, José a Buthriya', Buthriya' a Shu'ayb, Shu'ayb la entregó a Moisés b. 'Imran. Moisés b. 'Imran a Josué b. Nun, Josué b. Nun a David, David a Salomón, Salomón a Asif b. Barkhiyya, Asif b. Barkhiyya a Zacarías, Zacarías la entregó a Jesús b. María. Jesús a Simón b. Hammun al-Safa, Simón a Juan b. Zacarías, Juan b. Zacarías a Mundhir, Mundhir a Sulayma, Sulayma a Burda.",
    "fr": "Abraham légua à son fils Ismaël. Ismaël à Isaac, Isaac à Jacob, Jacob à Joseph, Joseph à Bouthriya', Bouthriya' à Chou'ayb, Chou'ayb la remit à Moïse b. 'Imran. Moïse b. 'Imran à Josué b. Noun, Josué b. Noun à David, David à Salomon, Salomon à Assif b. Barkhiyya, Assif b. Barkhiyya à Zacharie, Zacharie la remit à Jésus b. Marie. Jésus à Simon b. Ham'oun al-Safa, Simon à Jean b. Zacharie, Jean b. Zacharie à Moundhir, Moundhir à Soulayma, Soulayma à Bourda.",
    "de": "Abraham vermachte an seinen Sohn Ismael. Ismael an Isaak, Isaak an Jakob, Jakob an Joseph, Joseph an Buthrija', Buthrija' an Schu'aib, Schu'aib gab es Moses b. 'Imran. Moses b. 'Imran an Josua b. Nun, Josua b. Nun an David, David an Salomon, Salomon an Asif b. Barchija, Asif b. Barchija an Zacharias, Zacharias gab es Jesus b. Maria. Jesus an Simeon b. Hammun al-Safa, Simeon an Johannes b. Zacharias, Johannes b. Zacharias an Mundschir, Mundschir an Sulayma, Sulayma an Burda.",
    "ru": "Ибрахим завещал сыну Исмаилу. Исмаил Исхаку, Исхак Якубу, Якуб Юсуфу, Юсуф Бусрие, Бусрия Шуайбу, Шуайб передал Мусе ибн Имрану. Муса ибн Имран Юше ибн Нуну, Юша ибн Нун Давуду, Давуд Сулейману, Сулейман Асифу ибн Бархие, Асиф ибн Бархия Закарие, Закария передал Исе ибн Марьям. Иса Шамуну ибн Хаммуну ас-Сафа, Шамун Яхье ибн Закарие, Яхья ибн Закария Мунзиру, Мунзир Салиме, Салима Бурде.",
    "zh": "易卜拉欣嘱托了他的儿子伊斯玛仪。伊斯玛仪嘱托伊斯哈格，伊斯哈格嘱托叶尔孤白，叶尔孤白嘱托优素福，优素福嘱托布斯里亚，布斯里亚嘱托舒艾卜，舒艾卜交给穆萨·本·伊姆兰。穆萨·本·伊姆兰嘱托约书亚·本·努恩，约书亚·本·努恩嘱托达乌德，达乌德嘱托苏莱曼，苏莱曼嘱托阿西夫·本·巴尔希亚，阿西夫·本·巴尔希亚嘱托宰凯里亚，宰凯里亚交给尔萨·本·麦尔彦。尔萨嘱托舍蒙·本·哈蒙·萨法，舍蒙嘱托叶哈雅·本·宰凯里亚，叶哈雅·本·宰凯里亚嘱托蒙齐尔，蒙齐尔嘱托萨利玛，萨利玛嘱托布尔达。"
  }
}