{
  "word_analysis": [
    {
      "word": "حَدَّثَنَا",
      "translation": {
        "en": "narrated to us",
        "ur": "ہم سے بیان کیا",
        "tr": "bize rivayet etti",
        "fa": "برای ما روایت کرد",
        "id": "menceritakan kepada kami",
        "bn": "আমাদের বর্ণনা করেছেন",
        "es": "nos narró",
        "fr": "nous a rapporté",
        "de": "erzählte uns",
        "ru": "рассказал нам",
        "zh": "向我们讲述了"
      },
      "pos": "V"
    },
    {
      "word": "جَعْفَرُ",
      "translation": {
        "en": "Ja'far",
        "ur": "جعفر",
        "tr": "Ca'fer",
        "fa": "جعفر",
        "id": "Ja'far",
        "bn": "জা'ফর",
        "es": "Ja'far",
        "fr": "Ja'far",
        "de": "Ja'far",
        "ru": "Джафар",
        "zh": "贾法尔"
      },
      "pos": "N"
    },
    {
      "word": "بْنُ",
      "translation": {
        "en": "son of",
        "ur": "بن",
        "tr": "bin/oğlu",
        "fa": "بن",
        "id": "bin/putra",
        "bn": "ইবনে",
        "es": "hijo de",
        "fr": "fils de",
        "de": "Sohn von",
        "ru": "ибн/сын",
        "zh": "之子"
      },
      "pos": "N"
    },
    {
      "word": "مُحَمَّدِ",
      "translation": {
        "en": "Muhammad",
        "ur": "محمد",
        "tr": "Muhammed",
        "fa": "محمد",
        "id": "Muhammad",
        "bn": "মুহাম্মাদ",
        "es": "Muhammad",
        "fr": "Muhammad",
        "de": "Muhammad",
        "ru": "Мухаммад",
        "zh": "穆罕默德"
      },
      "pos": "N"
    },
    {
      "word": "بْنِ",
      "translation": {
        "en": "son of",
        "ur": "بن",
        "tr": "bin/oğlu",
        "fa": "بن",
        "id": "bin/putra",
        "bn": "ইবনে",
        "es": "hijo de",
        "fr": "fils de",
        "de": "Sohn von",
        "ru": "ибн/сын",
        "zh": "之子"
      },
      "pos": "N"
    },
    {
      "word": "مَسْرُورٍ",
      "translation": {
        "en": "Masrur",
        "ur": "مسرور",
        "tr": "Mesrur",
        "fa": "مسرور",
        "id": "Masrur",
        "bn": "মাসরুর",
        "es": "Masrur",
        "fr": "Masrur",
        "de": "Masrur",
        "ru": "Масрур",
        "zh": "马斯鲁尔"
      },
      "pos": "N"
    },
    {
      "word": "رَضِيَ",
      "translation": {
        "en": "may be pleased",
        "ur": "راضی ہو",
        "tr": "razı olsun",
        "fa": "خشنود باد",
        "id": "semoga ridha",
        "bn": "সন্তুষ্ট হোন",
        "es": "esté complacido",
        "fr": "soit satisfait",
        "de": "möge zufrieden sein",
        "ru": "да будет доволен",
        "zh": "愿…喜悦"
      },
      "pos": "V"
    },
    {
      "word": "اللَّهُ",
      "translation": {
        "en": "God",
        "ur": "اللہ",
        "tr": "Allah",
        "fa": "خدا",
        "id": "Allah",
        "bn": "আল্লাহ",
        "es": "Dios",
        "fr": "Dieu",
        "de": "Gott",
        "ru": "Аллах",
        "zh": "安拉"
      },
      "pos": "N"
    },
    {
      "word": "عَنْهُ",
      "translation": {
        "en": "with him",
        "ur": "اس سے",
        "tr": "ondan",
        "fa": "از او",
        "id": "darinya",
        "bn": "তাঁর প্রতি",
        "es": "con él",
        "fr": "de lui",
        "de": "mit ihm",
        "ru": "им",
        "zh": "于他"
      },
      "pos": "PREP"
    },
    {
      "word": "قَالَ",
      "translation": {
        "en": "he said",
        "ur": "اس نے کہا",
        "tr": "dedi",
        "fa": "گفت",
        "id": "berkata",
        "bn": "বলেছেন",
        "es": "dijo",
        "fr": "a dit",
        "de": "sagte",
        "ru": "сказал",
        "zh": "他说"
      },
      "pos": "V"
    },
    {
      "word": "حَدَّثَنَا",
      "translation": {
        "en": "narrated to us",
        "ur": "ہم سے بیان کیا",
        "tr": "bize rivayet etti",
        "fa": "برای ما روایت کرد",
        "id": "menceritakan kepada kami",
        "bn": "আমাদের বর্ণনা করেছেন",
        "es": "nos narró",
        "fr": "nous a rapporté",
        "de": "erzählte uns",
        "ru": "рассказал нам",
        "zh": "向我们讲述了"
      },
      "pos": "V"
    },
    {
      "word": "الْحُسَيْنُ",
      "translation": {
        "en": "al-Husayn",
        "ur": "حسین",
        "tr": "Hüseyin",
        "fa": "حسین",
        "id": "al-Husayn",
        "bn": "আল-হুসাইন",
        "es": "al-Husayn",
        "fr": "al-Husayn",
        "de": "al-Husayn",
        "ru": "аль-Хусайн",
        "zh": "侯赛因"
      },
      "pos": "N"
    },
    {
      "word": "ابْنُ",
      "translation": {
        "en": "son of",
        "ur": "بن",
        "tr": "bin/oğlu",
        "fa": "بن",
        "id": "bin/putra",
        "bn": "ইবনে",
        "es": "hijo de",
        "fr": "fils de",
        "de": "Sohn von",
        "ru": "ибн/сын",
        "zh": "之子"
      },
      "pos": "N"
    },
    {
      "word": "مُحَمَّدِ",
      "translation": {
        "en": "Muhammad",
        "ur": "محمد",
        "tr": "Muhammed",
        "fa": "محمد",
        "id": "Muhammad",
        "bn": "মুহাম্মাদ",
        "es": "Muhammad",
        "fr": "Muhammad",
        "de": "Muhammad",
        "ru": "Мухаммад",
        "zh": "穆罕默德"
      },
      "pos": "N"
    },
    {
      "word": "بْنِ",
      "translation": {
        "en": "son of",
        "ur": "بن",
        "tr": "bin/oğlu",
        "fa": "بن",
        "id": "bin/putra",
        "bn": "ইবনে",
        "es": "hijo de",
        "fr": "fils de",
        "de": "Sohn von",
        "ru": "ибн/сын",
        "zh": "之子"
      },
      "pos": "N"
    },
    {
      "word": "عَامِرٍ",
      "translation": {
        "en": "'Amer",
        "ur": "عامر",
        "tr": "Âmir",
        "fa": "عامر",
        "id": "'Amer",
        "bn": "আমের",
        "es": "'Amer",
        "fr": "'Amer",
        "de": "'Amer",
        "ru": "Амир",
        "zh": "阿米尔"
      },
      "pos": "N"
    },
    {
      "word": "عَنْ",
      "translation": {
        "en": "from",
        "ur": "سے",
        "tr": "-den",
        "fa": "از",
        "id": "dari",
        "bn": "থেকে",
        "es": "de",
        "fr": "de",
        "de": "von",
        "ru": "от",
        "zh": "从"
      },
      "pos": "PREP"
    },
    {
      "word": "عَمِّهِ",
      "translation": {
        "en": "his uncle",
        "ur": "اپنے چچا",
        "tr": "amcası",
        "fa": "عمویش",
        "id": "pamannya",
        "bn": "তাঁর চাচা",
        "es": "su tío",
        "fr": "son oncle",
        "de": "sein Onkel",
        "ru": "его дядя",
        "zh": "他的叔父"
      },
      "pos": "N"
    },
    {
      "word": "عَبْدِ",
      "translation": {
        "en": "servant of",
        "ur": "بندہ",
        "tr": "kulu",
        "fa": "بنده",
        "id": "hamba",
        "bn": "বান্দা",
        "es": "siervo de",
        "fr": "serviteur de",
        "de": "Diener von",
        "ru": "раб",
        "zh": "仆人"
      },
      "pos": "N"
    },
    {
      "word": "اللَّهِ",
      "translation": {
        "en": "God",
        "ur": "اللہ",
        "tr": "Allah",
        "fa": "الله",
        "id": "Allah",
        "bn": "আল্লাহ",
        "es": "Dios",
        "fr": "Dieu",
        "de": "Gott",
        "ru": "Аллах",
        "zh": "安拉"
      },
      "pos": "N"
    },
    {
      "word": "بْنِ",
      "translation": {
        "en": "son of",
        "ur": "بن",
        "tr": "bin/oğlu",
        "fa": "بن",
        "id": "bin/putra",
        "bn": "ইবনে",
        "es": "hijo de",
        "fr": "fils de",
        "de": "Sohn von",
        "ru": "ибн/сын",
        "zh": "之子"
      },
      "pos": "N"
    },
    {
      "word": "عَامِرٍ",
      "translation": {
        "en": "'Amer",
        "ur": "عامر",
        "tr": "Âmir",
        "fa": "عامر",
        "id": "'Amer",
        "bn": "আমের",
        "es": "'Amer",
        "fr": "'Amer",
        "de": "'Amer",
        "ru": "Амир",
        "zh": "阿米尔"
      },
      "pos": "N"
    },
    {
      "word": "عَنْ",
      "translation": {
        "en": "from",
        "ur": "سے",
        "tr": "-den",
        "fa": "از",
        "id": "dari",
        "bn": "থেকে",
        "es": "de",
        "fr": "de",
        "de": "von",
        "ru": "от",
        "zh": "从"
      },
      "pos": "PREP"
    },
    {
      "word": "مُحَمَّدِ",
      "translation": {
        "en": "Muhammad",
        "ur": "محمد",
        "tr": "Muhammed",
        "fa": "محمد",
        "id": "Muhammad",
        "bn": "মুহাম্মাদ",
        "es": "Muhammad",
        "fr": "Muhammad",
        "de": "Muhammad",
        "ru": "Мухаммад",
        "zh": "穆罕默德"
      },
      "pos": "N"
    },
    {
      "word": "بْنِ",
      "translation": {
        "en": "son of",
        "ur": "بن",
        "tr": "bin/oğlu",
        "fa": "بن",
        "id": "bin/putra",
        "bn": "ইবনে",
        "es": "hijo de",
        "fr": "fils de",
        "de": "Sohn von",
        "ru": "ибн/сын",
        "zh": "之子"
      },
      "pos": "N"
    },
    {
      "word": "زِيَادٍ",
      "translation": {
        "en": "Ziyad",
        "ur": "زیاد",
        "tr": "Ziyâd",
        "fa": "زیاد",
        "id": "Ziyad",
        "bn": "যিয়াদ",
        "es": "Ziyad",
        "fr": "Ziyad",
        "de": "Ziyad",
        "ru": "Зийад",
        "zh": "齐亚德"
      },
      "pos": "N"
    },
    {
      "word": "الْأَزْدِيِّ",
      "translation": {
        "en": "al-Azdi",
        "ur": "الازدی",
        "tr": "el-Ezdî",
        "fa": "الازدی",
        "id": "al-Azdi",
        "bn": "আল-আযদী",
        "es": "al-Azdi",
        "fr": "al-Azdi",
        "de": "al-Azdi",
        "ru": "аль-Азди",
        "zh": "阿兹迪"
      },
      "pos": "N"
    },
    {
      "word": "عَنْ",
      "translation": {
        "en": "from",
        "ur": "سے",
        "tr": "-den",
        "fa": "از",
        "id": "dari",
        "bn": "থেকে",
        "es": "de",
        "fr": "de",
        "de": "von",
        "ru": "от",
        "zh": "从"
      },
      "pos": "PREP"
    },
    {
      "word": "إِبْرَاهِيمَ",
      "translation": {
        "en": "Ibrahim",
        "ur": "ابراہیم",
        "tr": "İbrahim",
        "fa": "ابراهیم",
        "id": "Ibrahim",
        "bn": "ইবরাহীম",
        "es": "Ibrahim",
        "fr": "Ibrahim",
        "de": "Ibrahim",
        "ru": "Ибрахим",
        "zh": "易卜拉欣"
      },
      "pos": "N"
    },
    {
      "word": "ابْنِ",
      "translation": {
        "en": "son of",
        "ur": "بن",
        "tr": "bin/oğlu",
        "fa": "بن",
        "id": "bin/putra",
        "bn": "ইবনে",
        "es": "hijo de",
        "fr": "fils de",
        "de": "Sohn von",
        "ru": "ибн/сын",
        "zh": "之子"
      },
      "pos": "N"
    },
    {
      "word": "زِيَادٍ",
      "translation": {
        "en": "Ziyad",
        "ur": "زیاد",
        "tr": "Ziyâd",
        "fa": "زیاد",
        "id": "Ziyad",
        "bn": "যিয়াদ",
        "es": "Ziyad",
        "fr": "Ziyad",
        "de": "Ziyad",
        "ru": "Зийад",
        "zh": "齐亚德"
      },
      "pos": "N"
    },
    {
      "word": "الْكَرْخِيِّ",
      "translation": {
        "en": "al-Karkhi",
        "ur": "الکرخی",
        "tr": "el-Kerhî",
        "fa": "الکرخی",
        "id": "al-Karkhi",
        "bn": "আল-কারখী",
        "es": "al-Karkhi",
        "fr": "al-Karkhi",
        "de": "al-Karkhi",
        "ru": "аль-Кархи",
        "zh": "卡尔希"
      },
      "pos": "N"
    },
    {
      "word": "عَنِ",
      "translation": {
        "en": "from",
        "ur": "سے",
        "tr": "-den",
        "fa": "از",
        "id": "dari",
        "bn": "থেকে",
        "es": "de",
        "fr": "de",
        "de": "von",
        "ru": "от",
        "zh": "从"
      },
      "pos": "PREP"
    },
    {
      "word": "الصَّادِقِ",
      "translation": {
        "en": "al-Sadiq (the Truthful)",
        "ur": "صادق",
        "tr": "Sâdık",
        "fa": "صادق",
        "id": "al-Shadiq",
        "bn": "আস-সাদিক",
        "es": "al-Sadiq",
        "fr": "al-Sadiq",
        "de": "al-Sadiq",
        "ru": "ас-Садик",
        "zh": "萨迪克"
      },
      "pos": "N"
    },
    {
      "word": "جَعْفَرِ",
      "translation": {
        "en": "Ja'far",
        "ur": "جعفر",
        "tr": "Ca'fer",
        "fa": "جعفر",
        "id": "Ja'far",
        "bn": "জা'ফর",
        "es": "Ja'far",
        "fr": "Ja'far",
        "de": "Ja'far",
        "ru": "Джафар",
        "zh": "贾法尔"
      },
      "pos": "N"
    },
    {
      "word": "بْنِ",
      "translation": {
        "en": "son of",
        "ur": "بن",
        "tr": "bin/oğlu",
        "fa": "بن",
        "id": "bin/putra",
        "bn": "ইবনে",
        "es": "hijo de",
        "fr": "fils de",
        "de": "Sohn von",
        "ru": "ибн/сын",
        "zh": "之子"
      },
      "pos": "N"
    },
    {
      "word": "مُحَمَّدٍ",
      "translation": {
        "en": "Muhammad",
        "ur": "محمد",
        "tr": "Muhammed",
        "fa": "محمد",
        "id": "Muhammad",
        "bn": "মুহাম্মাদ",
        "es": "Muhammad",
        "fr": "Muhammad",
        "de": "Muhammad",
        "ru": "Мухаммад",
        "zh": "穆罕默德"
      },
      "pos": "N"
    },
    {
      "word": "عَلَيْهِمَا",
      "translation": {
        "en": "upon them both",
        "ur": "ان دونوں پر",
        "tr": "ikisine de",
        "fa": "بر هر دوی آنها",
        "id": "atas keduanya",
        "bn": "তাঁদের উভয়ের উপর",
        "es": "sobre ambos",
        "fr": "sur eux deux",
        "de": "auf ihnen beiden",
        "ru": "на них обоих",
        "zh": "在他们二者之上"
      },
      "pos": "PREP"
    },
    {
      "word": "السَّلَامُ",
      "translation": {
        "en": "peace",
        "ur": "سلام",
        "tr": "selam",
        "fa": "سلام",
        "id": "salam/kedamaian",
        "bn": "শান্তি",
        "es": "paz",
        "fr": "paix",
        "de": "Friede",
        "ru": "мир",
        "zh": "平安"
      },
      "pos": "N"
    },
    {
      "word": "قَالَ",
      "translation": {
        "en": "he said",
        "ur": "فرمایا",
        "tr": "buyurdu",
        "fa": "فرمود",
        "id": "bersabda",
        "bn": "বলেছেন",
        "es": "dijo",
        "fr": "a dit",
        "de": "sagte",
        "ru": "сказал",
        "zh": "他说"
      },
      "pos": "V"
    }
  ],
  "translations": {
    "en": "Ja'far ibn Muhammad ibn Masrur (may God be pleased with him) narrated to us. He said: al-Husayn ibn Muhammad ibn 'Amer narrated to us, from his uncle 'Abdullah ibn 'Amer, from Muhammad ibn Ziyad al-Azdi, from Ibrahim ibn Ziyad al-Karkhi, from al-Sadiq Ja'far ibn Muhammad (peace be upon them both). He said:",
    "ur": "ہم سے جعفر بن محمد بن مسرور (رضی اللہ عنہ) نے بیان کیا، انہوں نے کہا: ہم سے حسین بن محمد بن عامر نے بیان کیا، اپنے چچا عبد اللہ بن عامر سے، محمد بن زیاد الازدی سے، ابراہیم بن زیاد الکرخی سے، صادق جعفر بن محمد (علیہما السلام) سے۔ فرمایا:",
    "tr": "Bize Ca'fer b. Muhammed b. Mesrur (radıyallahu anh) rivayet etti. Dedi ki: Bize Hüseyin b. Muhammed b. Âmir rivayet etti, amcası Abdullah b. Âmir'den, Muhammed b. Ziyâd el-Ezdî'den, İbrahim b. Ziyâd el-Kerhî'den, Sâdık Ca'fer b. Muhammed'den (aleyhimesselam). Buyurdu ki:",
    "fa": "جعفر بن محمد بن مسرور (رضی الله عنه) برای ما روایت کرد، گفت: حسین بن محمد بن عامر برای ما روایت کرد، از عمویش عبد الله بن عامر، از محمد بن زیاد ازدی، از ابراهیم بن زیاد کرخی، از صادق جعفر بن محمد (علیهما السلام). فرمود:",
    "id": "Ja'far bin Muhammad bin Masrur (semoga Allah meridhainya) menceritakan kepada kami. Dia berkata: Al-Husayn bin Muhammad bin 'Amer menceritakan kepada kami, dari pamannya 'Abdullah bin 'Amer, dari Muhammad bin Ziyad al-Azdi, dari Ibrahim bin Ziyad al-Karkhi, dari al-Shadiq Ja'far bin Muhammad (semoga kedamaian atas keduanya). Beliau bersabda:",
    "bn": "জা'ফর ইবনে মুহাম্মাদ ইবনে মাসরুর (রাদিয়াল্লাহু আনহু) আমাদের বর্ণনা করেছেন। তিনি বলেছেন: আল-হুসাইন ইবনে মুহাম্মাদ ইবনে আমের আমাদের বর্ণনা করেছেন, তাঁর চাচা আব্দুল্লাহ ইবনে আমের থেকে, মুহাম্মাদ ইবনে যিয়াদ আল-আযদী থেকে, ইবরাহীম ইবনে যিয়াদ আল-কারখী থেকে, আস-সাদিক জা'ফর ইবনে মুহাম্মাদ (আলাইহিমাস সালাম) থেকে। তিনি বলেছেন:",
    "es": "Ja'far ibn Muhammad ibn Masrur (que Dios esté complacido con él) nos narró. Dijo: Al-Husayn ibn Muhammad ibn 'Amer nos narró, de su tío 'Abdullah ibn 'Amer, de Muhammad ibn Ziyad al-Azdi, de Ibrahim ibn Ziyad al-Karkhi, de al-Sadiq Ja'far ibn Muhammad (la paz sea con ambos). Dijo:",
    "fr": "Ja'far ibn Muhammad ibn Masrur (que Dieu soit satisfait de lui) nous a rapporté. Il a dit : al-Husayn ibn Muhammad ibn 'Amer nous a rapporté, de son oncle 'Abdullah ibn 'Amer, de Muhammad ibn Ziyad al-Azdi, d'Ibrahim ibn Ziyad al-Karkhi, d'al-Sadiq Ja'far ibn Muhammad (que la paix soit sur eux deux). Il a dit :",
    "de": "Ja'far ibn Muhammad ibn Masrur (möge Gott mit ihm zufrieden sein) erzählte uns. Er sagte: al-Husayn ibn Muhammad ibn 'Amer erzählte uns, von seinem Onkel 'Abdullah ibn 'Amer, von Muhammad ibn Ziyad al-Azdi, von Ibrahim ibn Ziyad al-Karkhi, von al-Sadiq Ja'far ibn Muhammad (Friede sei mit ihnen beiden). Er sagte:",
    "ru": "Джафар ибн Мухаммад ибн Масрур (да будет доволен им Аллах) рассказал нам. Он сказал: аль-Хусайн ибн Мухаммад ибн Амир рассказал нам, от своего дяди Абдуллаха ибн Амира, от Мухаммада ибн Зийада аль-Азди, от Ибрахима ибн Зийада аль-Кархи, от ас-Садика Джафара ибн Мухаммада (мир им обоим). Он сказал:",
    "zh": "贾法尔·本·穆罕默德·本·马斯鲁尔（愿安拉喜悦他）向我们讲述了。他说：侯赛因·本·穆罕默德·本·阿米尔向我们讲述了，从他的叔父阿卜杜拉·本·阿米尔，从穆罕默德·本·齐亚德·阿兹迪，从易卜拉欣·本·齐亚德·卡尔希，从萨迪克·贾法尔·本·穆罕默德（愿他们二者平安）。他说："
  }
}