{
  "word_analysis": [
    {
      "word": "عَنْكُمْ",
      "translation": {
        "en": "from you (pl.)",
        "ur": "آپ لوگوں سے",
        "tr": "sizden",
        "fa": "از شما",
        "id": "dari kalian",
        "bn": "আপনাদের কাছ থেকে",
        "es": "de vosotros",
        "fr": "de vous",
        "de": "von euch",
        "ru": "от вас",
        "zh": "来自你们"
      },
      "pos": "PREP"
    },
    {
      "word": "فَنَأْخُذُ",
      "translation": {
        "en": "so we take/adopt",
        "ur": "تو ہم اخذ کرتے ہیں",
        "tr": "öyle alırız",
        "fa": "پس می‌گیریم",
        "id": "maka kami mengambil",
        "bn": "তাই আমরা গ্রহণ করি",
        "es": "así que tomamos",
        "fr": "alors nous prenons",
        "de": "so nehmen wir",
        "ru": "и мы берём",
        "zh": "于是我们采用"
      },
      "pos": "V"
    },
    {
      "word": "بِهِ",
      "translation": {
        "en": "by it",
        "ur": "اسے",
        "tr": "onunla",
        "fa": "به آن",
        "id": "dengannya",
        "bn": "তা অনুসরণ করি",
        "es": "con ello",
        "fr": "par cela",
        "de": "damit",
        "ru": "этим",
        "zh": "用它"
      },
      "pos": "PREP"
    },
    {
      "word": "فَقَالَ",
      "translation": {
        "en": "so he said",
        "ur": "تو آپ نے فرمایا",
        "tr": "o da dedi",
        "fa": "پس فرمود",
        "id": "maka ia berkata",
        "bn": "তখন তিনি বললেন",
        "es": "entonces dijo",
        "fr": "alors il dit",
        "de": "so sagte er",
        "ru": "тогда он сказал",
        "zh": "于是他说"
      },
      "pos": "V"
    },
    {
      "word": "هَيْهَاتَ",
      "translation": {
        "en": "Far be it!",
        "ur": "ہرگز نہیں!",
        "tr": "Hâşâ!",
        "fa": "هیهات!",
        "id": "Sungguh jauh!",
        "bn": "কত দূরের কথা!",
        "es": "¡Lejos de eso!",
        "fr": "Loin de là !",
        "de": "Fern sei das!",
        "ru": "Далеко от этого!",
        "zh": "岂能如此！"
      },
      "pos": "INTJ"
    },
    {
      "word": "هَيْهَاتَ",
      "translation": {
        "en": "Far be it!",
        "ur": "ہرگز نہیں!",
        "tr": "Hâşâ!",
        "fa": "هیهات!",
        "id": "Sungguh jauh!",
        "bn": "কত দূরের কথা!",
        "es": "¡Lejos de eso!",
        "fr": "Loin de là !",
        "de": "Fern sei das!",
        "ru": "Далеко от этого!",
        "zh": "岂能如此！"
      },
      "pos": "INTJ"
    },
    {
      "word": "فِي",
      "translation": {
        "en": "in/by",
        "ur": "اس میں",
        "tr": "bununla",
        "fa": "به خاطر",
        "id": "dalam hal",
        "bn": "এতে",
        "es": "en eso",
        "fr": "en cela",
        "de": "darin",
        "ru": "в этом",
        "zh": "在这当中"
      },
      "pos": "PREP"
    },
    {
      "word": "ذَلِكَ",
      "translation": {
        "en": "that",
        "ur": "یہ",
        "tr": "o/şu",
        "fa": "آن",
        "id": "itu",
        "bn": "এটার",
        "es": "eso",
        "fr": "cela",
        "de": "das",
        "ru": "это",
        "zh": "那"
      },
      "pos": "DEM"
    },
    {
      "word": "وَاللَّهِ",
      "translation": {
        "en": "by God",
        "ur": "اللہ کی قسم",
        "tr": "Allah'a yemin olsun",
        "fa": "به خدا",
        "id": "demi Allah",
        "bn": "আল্লাহর কসম",
        "es": "por Dios",
        "fr": "par Dieu",
        "de": "bei Gott",
        "ru": "клянусь Аллахом",
        "zh": "凭真主"
      },
      "pos": "N"
    },
    {
      "word": "هَلَكَ",
      "translation": {
        "en": "was destroyed/perished",
        "ur": "ہلاک ہوا",
        "tr": "helak oldu",
        "fa": "هلاک شد",
        "id": "binasa",
        "bn": "ধ্বংস হলো",
        "es": "pereció",
        "fr": "périt",
        "de": "verdarb",
        "ru": "погиб",
        "zh": "毁灭了"
      },
      "pos": "V"
    },
    {
      "word": "مَنْ",
      "translation": {
        "en": "whoever",
        "ur": "جو",
        "tr": "kim",
        "fa": "هر که",
        "id": "siapa",
        "bn": "যে",
        "es": "quien",
        "fr": "celui qui",
        "de": "wer",
        "ru": "кто",
        "zh": "谁"
      },
      "pos": "PRON"
    },
    {
      "word": "هَلَكَ",
      "translation": {
        "en": "perished",
        "ur": "ہلاک ہوا",
        "tr": "helak oldu",
        "fa": "هلاک شد",
        "id": "binasa",
        "bn": "ধ্বংস হয়েছে",
        "es": "pereció",
        "fr": "périt",
        "de": "verdarb",
        "ru": "погиб",
        "zh": "毁灭"
      },
      "pos": "V"
    },
    {
      "word": "يَا",
      "translation": {
        "en": "O",
        "ur": "اے",
        "tr": "ey",
        "fa": "ای",
        "id": "wahai",
        "bn": "হে",
        "es": "oh",
        "fr": "ô",
        "de": "O",
        "ru": "о",
        "zh": "哦"
      },
      "pos": "PART"
    },
    {
      "word": "ابْنَ",
      "translation": {
        "en": "son of",
        "ur": "بن",
        "tr": "oğlu",
        "fa": "پسر",
        "id": "putra",
        "bn": "পুত্র",
        "es": "hijo de",
        "fr": "fils de",
        "de": "Sohn des",
        "ru": "сын",
        "zh": "之子"
      },
      "pos": "N"
    },
    {
      "word": "حَكِيمٍ",
      "translation": {
        "en": "Hakim",
        "ur": "حکیم",
        "tr": "Hakîm",
        "fa": "حکیم",
        "id": "Hakim",
        "bn": "হাকিম",
        "es": "Hakim",
        "fr": "Hakim",
        "de": "Hakim",
        "ru": "Хакима",
        "zh": "哈基姆"
      },
      "pos": "N"
    },
    {
      "word": "قَالَ",
      "translation": {
        "en": "he said",
        "ur": "اس نے کہا",
        "tr": "dedi",
        "fa": "گفت",
        "id": "ia berkata",
        "bn": "তিনি বললেন",
        "es": "dijo",
        "fr": "dit",
        "de": "sagte er",
        "ru": "сказал",
        "zh": "他说"
      },
      "pos": "V"
    },
    {
      "word": "ثُمَّ",
      "translation": {
        "en": "then",
        "ur": "پھر",
        "tr": "sonra",
        "fa": "سپس",
        "id": "kemudian",
        "bn": "তারপর",
        "es": "luego",
        "fr": "puis",
        "de": "dann",
        "ru": "затем",
        "zh": "然后"
      },
      "pos": "CONJ"
    },
    {
      "word": "قَالَ",
      "translation": {
        "en": "he said",
        "ur": "اس نے کہا",
        "tr": "dedi",
        "fa": "فرمود",
        "id": "ia berkata",
        "bn": "তিনি বললেন",
        "es": "dijo",
        "fr": "dit",
        "de": "sagte er",
        "ru": "сказал",
        "zh": "他说"
      },
      "pos": "V"
    },
    {
      "word": "لَعَنَ",
      "translation": {
        "en": "may curse",
        "ur": "لعنت کرے",
        "tr": "lanet etsin",
        "fa": "لعنت کند",
        "id": "semoga Allah melaknat",
        "bn": "অভিশাপ দিন",
        "es": "maldiga",
        "fr": "maudisse",
        "de": "verfluche",
        "ru": "да проклянёт",
        "zh": "愿安拉诅咒"
      },
      "pos": "V"
    },
    {
      "word": "اللَّهُ",
      "translation": {
        "en": "God",
        "ur": "اللہ",
        "tr": "Allah",
        "fa": "خدا",
        "id": "Allah",
        "bn": "আল্লাহ",
        "es": "Dios",
        "fr": "Dieu",
        "de": "Gott",
        "ru": "Аллах",
        "zh": "安拉"
      },
      "pos": "N"
    },
    {
      "word": "أَبَا",
      "translation": {
        "en": "Abu",
        "ur": "ابو",
        "tr": "Ebu",
        "fa": "ابو",
        "id": "Abu",
        "bn": "আবু",
        "es": "Abu",
        "fr": "Abu",
        "de": "Abu",
        "ru": "Абу",
        "zh": "阿布"
      },
      "pos": "N"
    },
    {
      "word": "حَنِيفَةَ",
      "translation": {
        "en": "Hanifa",
        "ur": "حنیفہ",
        "tr": "Hanîfe",
        "fa": "حنیفه",
        "id": "Hanifah",
        "bn": "হানিফা",
        "es": "Hanifa",
        "fr": "Hanifa",
        "de": "Hanifa",
        "ru": "Ханифы",
        "zh": "哈尼法"
      },
      "pos": "N"
    },
    {
      "word": "كَانَ",
      "translation": {
        "en": "he used to",
        "ur": "وہ کرتا تھا",
        "tr": "idi",
        "fa": "می‌کرد",
        "id": "ia selalu",
        "bn": "সে করত",
        "es": "solía",
        "fr": "avait l'habitude de",
        "de": "pflegte zu",
        "ru": "он обычно",
        "zh": "他惯常"
      },
      "pos": "V"
    },
    {
      "word": "يَقُولُ",
      "translation": {
        "en": "say",
        "ur": "کہنا",
        "tr": "söylemek",
        "fa": "می‌گفت",
        "id": "berkata",
        "bn": "বলত",
        "es": "decir",
        "fr": "dire",
        "de": "sagen",
        "ru": "говорить",
        "zh": "说"
      },
      "pos": "V"
    },
    {
      "word": "قَالَ",
      "translation": {
        "en": "Ali said",
        "ur": "علی نے فرمایا",
        "tr": "Ali dedi",
        "fa": "علی گفت",
        "id": "Ali berkata",
        "bn": "আলী বলেছেন",
        "es": "Ali dijo",
        "fr": "Ali a dit",
        "de": "Ali sagte",
        "ru": "Али сказал",
        "zh": "阿里说"
      },
      "pos": "V"
    },
    {
      "word": "عَلِيٌّ",
      "translation": {
        "en": "Ali",
        "ur": "علی",
        "tr": "Ali",
        "fa": "علی",
        "id": "Ali",
        "bn": "আলী",
        "es": "Ali",
        "fr": "Ali",
        "de": "Ali",
        "ru": "Али",
        "zh": "阿里"
      },
      "pos": "N"
    },
    {
      "word": "وَقُلْتُ",
      "translation": {
        "en": "and I say",
        "ur": "اور میں کہتا ہوں",
        "tr": "ve ben diyorum",
        "fa": "و من می‌گویم",
        "id": "dan aku berkata",
        "bn": "এবং আমি বলি",
        "es": "y yo digo",
        "fr": "et je dis",
        "de": "und ich sage",
        "ru": "и я говорю",
        "zh": "而我说"
      },
      "pos": "V"
    }
  ],
  "translations": {
    "en": "He said: 'Far be it! Far be it! By God, whoever perished, perished by that, O Ibn Hakim!' He then said: 'May God curse Abu Hanifa! He used to say, \"Ali said, and I say.\"'",
    "ur": "آپ نے فرمایا: ہرگز نہیں! ہرگز نہیں! اس میں، اللہ کی قسم، جو ہلاک ہوا وہ ہلاک ہوا، اے ابن حکیم! پھر آپ نے فرمایا: اللہ ابو حنیفہ پر لعنت کرے، وہ کہتا تھا: علی نے یہ فرمایا اور میں کہتا ہوں۔",
    "tr": "Dedi ki: 'Hâşâ! Hâşâ! Allah'a yemin olsun, helak olan, bununla helak oldu, ey İbn Hakîm!' Sonra dedi: 'Allah, Ebu Hanîfe'yi lanet etsin! O şöyle derdi: Ali dedi, ben de derim.'",
    "fa": "فرمودند: هیهات! هیهات! به خدا، هر که هلاک شد به خاطر همین هلاک شد، ای پسر حکیم! سپس فرمودند: خداوند ابوحنیفه را لعنت کند! او می‌گفت: علی گفت و من هم می‌گویم.",
    "id": "Ia berkata: 'Sungguh jauh! Sungguh jauh! Demi Allah, siapa yang binasa, binasalah karena itu, wahai Ibn Hakim!' Kemudian ia berkata: 'Semoga Allah melaknat Abu Hanifah! Ia biasa berkata, \"Ali berkata, dan aku berkata.\"'",
    "bn": "তিনি বললেন: 'কত দূরের কথা! কত দূরের কথা! আল্লাহর কসম, যে ধ্বংস হয়েছে এতেই ধ্বংস হয়েছে, হে ইবনে হাকিম!' তারপর বললেন: 'আল্লাহ আবু হানিফাকে অভিশাপ দিন! সে বলত, আলী বলেছেন এবং আমি বলছি।'",
    "es": "Dijo: '¡Lejos de eso! ¡Lejos de eso! Por Dios, quien pereció, pereció por eso, ¡O Ibn Hakim!' Luego dijo: '¡Que Dios maldiga a Abu Hanifa! Solía decir: Ali dijo, y yo digo.'",
    "fr": "Il dit : « Loin de là ! Loin de là ! Par Dieu, quiconque a péri a péri par cela, ô Ibn Hakim ! » Puis il dit : « Que Dieu maudisse Abu Hanifa ! Il avait l'habitude de dire : Ali a dit, et moi je dis. »",
    "de": "Er sagte: 'Fern sei das! Fern sei das! Bei Gott, wer zugrunde ging, ging dadurch zugrunde, O Ibn Hakim!' Dann sagte er: 'Möge Gott Abu Hanifa verfluchen! Er pflegte zu sagen: Ali sagte, und ich sage.'",
    "ru": "Он сказал: «Далеко от этого! Далеко от этого! Клянусь Аллахом, кто погиб — погиб из-за этого, о Ибн Хаким!» Затем сказал: «Да проклянёт Аллах Абу Ханифу! Он обычно говорил: Али сказал, и я говорю.»",
    "zh": "他说：「岂能如此！岂能如此！凭真主，谁毁灭了，就是因此而毁灭的，O伊本·哈基姆！」然后他说：「愿真主诅咒艾布·哈尼法！他惯常说：阿里说了，我也说。」"
  }
}