{
  "word_analysis": [
    {
      "word": "حَدَّثَنَا",
      "translation": {
        "en": "narrated to us",
        "ur": "ہم سے بیان کیا",
        "tr": "bize rivayet etti",
        "fa": "برای ما روایت کرد",
        "id": "menceritakan kepada kami",
        "bn": "আমাদের বর্ণনা করেছেন",
        "es": "nos narró",
        "fr": "nous a raconté",
        "de": "berichtete uns",
        "ru": "рассказал нам",
        "zh": "给我们讲述了"
      },
      "pos": "V"
    },
    {
      "word": "مُحَمَّدُ",
      "translation": {
        "en": "Muhammad",
        "ur": "محمد",
        "tr": "Muhammed",
        "fa": "محمد",
        "id": "Muhammad",
        "bn": "মুহাম্মাদ",
        "es": "Muhammad",
        "fr": "Muhammad",
        "de": "Muhammad",
        "ru": "Мухаммад",
        "zh": "穆罕默德"
      },
      "pos": "N"
    },
    {
      "word": "بْنُ",
      "translation": {
        "en": "son of",
        "ur": "بن",
        "tr": "bin/oğlu",
        "fa": "بن",
        "id": "bin/putra",
        "bn": "ইবনে",
        "es": "hijo de",
        "fr": "fils de",
        "de": "Sohn von",
        "ru": "ибн/сын",
        "zh": "之子"
      },
      "pos": "N"
    },
    {
      "word": "الْحَسَنِ",
      "translation": {
        "en": "al-Hasan",
        "ur": "الحسن",
        "tr": "el-Hasen",
        "fa": "الحسن",
        "id": "al-Hasan",
        "bn": "আল-হাসান",
        "es": "al-Hasan",
        "fr": "al-Hasan",
        "de": "al-Hasan",
        "ru": "аль-Хасан",
        "zh": "哈桑"
      },
      "pos": "N"
    },
    {
      "word": "قَالَ",
      "translation": {
        "en": "he said",
        "ur": "اس نے کہا",
        "tr": "dedi",
        "fa": "گفت",
        "id": "dia berkata",
        "bn": "তিনি বললেন",
        "es": "dijo",
        "fr": "il a dit",
        "de": "er sagte",
        "ru": "он сказал",
        "zh": "他说"
      },
      "pos": "V"
    },
    {
      "word": "حَدَّثَنَا",
      "translation": {
        "en": "narrated to us",
        "ur": "ہم سے بیان کیا",
        "tr": "bize rivayet etti",
        "fa": "برای ما روایت کرد",
        "id": "menceritakan kepada kami",
        "bn": "আমাদের বর্ণনা করেছেন",
        "es": "nos narró",
        "fr": "nous a raconté",
        "de": "berichtete uns",
        "ru": "рассказал нам",
        "zh": "给我们讲述了"
      },
      "pos": "V"
    },
    {
      "word": "أَحْمَدُ",
      "translation": {
        "en": "Ahmad",
        "ur": "احمد",
        "tr": "Ahmed",
        "fa": "احمد",
        "id": "Ahmad",
        "bn": "আহমাদ",
        "es": "Ahmad",
        "fr": "Ahmad",
        "de": "Ahmad",
        "ru": "Ахмад",
        "zh": "艾哈迈德"
      },
      "pos": "N"
    },
    {
      "word": "بْنُ",
      "translation": {
        "en": "son of",
        "ur": "بن",
        "tr": "bin/oğlu",
        "fa": "بن",
        "id": "bin/putra",
        "bn": "ইবনে",
        "es": "hijo de",
        "fr": "fils de",
        "de": "Sohn von",
        "ru": "ибн/сын",
        "zh": "之子"
      },
      "pos": "N"
    },
    {
      "word": "إِدْرِيسَ",
      "translation": {
        "en": "Idris",
        "ur": "ادریس",
        "tr": "İdris",
        "fa": "ادریس",
        "id": "Idris",
        "bn": "ইদরিস",
        "es": "Idris",
        "fr": "Idris",
        "de": "Idris",
        "ru": "Идрис",
        "zh": "伊德里斯"
      },
      "pos": "N"
    },
    {
      "word": "عَنْ",
      "translation": {
        "en": "from",
        "ur": "سے",
        "tr": "-den",
        "fa": "از",
        "id": "dari",
        "bn": "থেকে",
        "es": "de",
        "fr": "de",
        "de": "von",
        "ru": "от",
        "zh": "从"
      },
      "pos": "PREP"
    },
    {
      "word": "مُحَمَّدِ",
      "translation": {
        "en": "Muhammad",
        "ur": "محمد",
        "tr": "Muhammed",
        "fa": "محمد",
        "id": "Muhammad",
        "bn": "মুহাম্মাদ",
        "es": "Muhammad",
        "fr": "Muhammad",
        "de": "Muhammad",
        "ru": "Мухаммад",
        "zh": "穆罕默德"
      },
      "pos": "N"
    },
    {
      "word": "ابْنِ",
      "translation": {
        "en": "son of",
        "ur": "بن",
        "tr": "bin/oğlu",
        "fa": "بن",
        "id": "bin/putra",
        "bn": "ইবনে",
        "es": "hijo de",
        "fr": "fils de",
        "de": "Sohn von",
        "ru": "ибн/сын",
        "zh": "之子"
      },
      "pos": "N"
    },
    {
      "word": "أَحْمَدَ",
      "translation": {
        "en": "Ahmad",
        "ur": "احمد",
        "tr": "Ahmed",
        "fa": "احمد",
        "id": "Ahmad",
        "bn": "আহমাদ",
        "es": "Ahmad",
        "fr": "Ahmad",
        "de": "Ahmad",
        "ru": "Ахмад",
        "zh": "艾哈迈德"
      },
      "pos": "N"
    },
    {
      "word": "عَنْ",
      "translation": {
        "en": "from",
        "ur": "سے",
        "tr": "-den",
        "fa": "از",
        "id": "dari",
        "bn": "থেকে",
        "es": "de",
        "fr": "de",
        "de": "von",
        "ru": "от",
        "zh": "从"
      },
      "pos": "PREP"
    },
    {
      "word": "عَلِيِّ",
      "translation": {
        "en": "Ali",
        "ur": "علی",
        "tr": "Ali",
        "fa": "علی",
        "id": "Ali",
        "bn": "আলী",
        "es": "Ali",
        "fr": "Ali",
        "de": "Ali",
        "ru": "Али",
        "zh": "阿里"
      },
      "pos": "N"
    },
    {
      "word": "بْنِ",
      "translation": {
        "en": "son of",
        "ur": "بن",
        "tr": "bin/oğlu",
        "fa": "بن",
        "id": "bin/putra",
        "bn": "ইবনে",
        "es": "hijo de",
        "fr": "fils de",
        "de": "Sohn von",
        "ru": "ибн/сын",
        "zh": "之子"
      },
      "pos": "N"
    },
    {
      "word": "إِسْمَاعِيلَ",
      "translation": {
        "en": "Ismail",
        "ur": "اسماعیل",
        "tr": "İsmail",
        "fa": "اسماعیل",
        "id": "Ismail",
        "bn": "ইসমাইল",
        "es": "Ismail",
        "fr": "Ismaïl",
        "de": "Ismail",
        "ru": "Исмаил",
        "zh": "伊斯玛仪"
      },
      "pos": "N"
    },
    {
      "word": "عَنْ",
      "translation": {
        "en": "from",
        "ur": "سے",
        "tr": "-den",
        "fa": "از",
        "id": "dari",
        "bn": "থেকে",
        "es": "de",
        "fr": "de",
        "de": "von",
        "ru": "от",
        "zh": "从"
      },
      "pos": "PREP"
    },
    {
      "word": "مُحَمَّدِ",
      "translation": {
        "en": "Muhammad",
        "ur": "محمد",
        "tr": "Muhammed",
        "fa": "محمد",
        "id": "Muhammad",
        "bn": "মুহাম্মাদ",
        "es": "Muhammad",
        "fr": "Muhammad",
        "de": "Muhammad",
        "ru": "Мухаммад",
        "zh": "穆罕默德"
      },
      "pos": "N"
    },
    {
      "word": "بْنِ",
      "translation": {
        "en": "son of",
        "ur": "بن",
        "tr": "bin/oğlu",
        "fa": "بن",
        "id": "bin/putra",
        "bn": "ইবনে",
        "es": "hijo de",
        "fr": "fils de",
        "de": "Sohn von",
        "ru": "ибн/сын",
        "zh": "之子"
      },
      "pos": "N"
    },
    {
      "word": "عَمْرٍو",
      "translation": {
        "en": "Amr",
        "ur": "عمرو",
        "tr": "Amr",
        "fa": "عمرو",
        "id": "Amr",
        "bn": "আমর",
        "es": "Amr",
        "fr": "Amr",
        "de": "Amr",
        "ru": "Амр",
        "zh": "阿姆尔"
      },
      "pos": "N"
    },
    {
      "word": "الزَّيَّاتِ",
      "translation": {
        "en": "al-Zayyat (the oil seller)",
        "ur": "الزیات (تیل فروش)",
        "tr": "ez-Zeyyât (yağcı)",
        "fa": "الزیات (روغن‌فروش)",
        "id": "al-Zayyat (penjual minyak)",
        "bn": "আল-যাইয়াত (তেল বিক্রেতা)",
        "es": "al-Zayyat (el vendedor de aceite)",
        "fr": "al-Zayyât (le marchand d'huile)",
        "de": "al-Zayyat (der Ölhändler)",
        "ru": "аз-Заййат (торговец маслом)",
        "zh": "扎亚特（油商）"
      },
      "pos": "N"
    },
    {
      "word": "عَنْ",
      "translation": {
        "en": "from",
        "ur": "سے",
        "tr": "-den",
        "fa": "از",
        "id": "dari",
        "bn": "থেকে",
        "es": "de",
        "fr": "de",
        "de": "von",
        "ru": "от",
        "zh": "从"
      },
      "pos": "PREP"
    },
    {
      "word": "فَائِدٍ",
      "translation": {
        "en": "Fa'id",
        "ur": "فائد",
        "tr": "Fâid",
        "fa": "فائد",
        "id": "Fa'id",
        "bn": "ফায়িদ",
        "es": "Fa'id",
        "fr": "Fâ'id",
        "de": "Fa'id",
        "ru": "Фаид",
        "zh": "法伊德"
      },
      "pos": "N"
    },
    {
      "word": "الْحَنَّاطِ",
      "translation": {
        "en": "al-Hannat (the wheat seller)",
        "ur": "الحناط (گندم فروش)",
        "tr": "el-Hannât (buğdaycı)",
        "fa": "الحناط (گندم‌فروش)",
        "id": "al-Hannat (penjual gandum)",
        "bn": "আল-হান্নাত (গম বিক্রেতা)",
        "es": "al-Hannat (el vendedor de trigo)",
        "fr": "al-Hannât (le marchand de blé)",
        "de": "al-Hannat (der Weizenhändler)",
        "ru": "аль-Ханнат (торговец пшеницей)",
        "zh": "汉纳特（麦商）"
      },
      "pos": "N"
    },
    {
      "word": "عَنْ",
      "translation": {
        "en": "from",
        "ur": "سے",
        "tr": "-den",
        "fa": "از",
        "id": "dari",
        "bn": "থেকে",
        "es": "de",
        "fr": "de",
        "de": "von",
        "ru": "от",
        "zh": "从"
      },
      "pos": "PREP"
    },
    {
      "word": "أَبِي",
      "translation": {
        "en": "Abu (father of)",
        "ur": "ابو (والد)",
        "tr": "Ebu (babası)",
        "fa": "ابو (پدر)",
        "id": "Abu (ayah dari)",
        "bn": "আবু (পিতা)",
        "es": "Abu (padre de)",
        "fr": "Abou (père de)",
        "de": "Abu (Vater von)",
        "ru": "Абу (отец)",
        "zh": "阿布（之父）"
      },
      "pos": "N"
    },
    {
      "word": "الْحَسَنِ",
      "translation": {
        "en": "al-Hasan",
        "ur": "الحسن",
        "tr": "el-Hasen",
        "fa": "الحسن",
        "id": "al-Hasan",
        "bn": "আল-হাসান",
        "es": "al-Hasan",
        "fr": "al-Hasan",
        "de": "al-Hasan",
        "ru": "аль-Хасан",
        "zh": "哈桑"
      },
      "pos": "N"
    },
    {
      "word": "مُوسَى",
      "translation": {
        "en": "Musa",
        "ur": "موسیٰ",
        "tr": "Mûsâ",
        "fa": "موسی",
        "id": "Musa",
        "bn": "মূসা",
        "es": "Musa",
        "fr": "Moûsâ",
        "de": "Musa",
        "ru": "Муса",
        "zh": "穆萨"
      },
      "pos": "N"
    },
    {
      "word": "بْنِ",
      "translation": {
        "en": "son of",
        "ur": "بن",
        "tr": "bin/oğlu",
        "fa": "بن",
        "id": "bin/putra",
        "bn": "ইবনে",
        "es": "hijo de",
        "fr": "fils de",
        "de": "Sohn von",
        "ru": "ибн/сын",
        "zh": "之子"
      },
      "pos": "N"
    },
    {
      "word": "جَعْفَرٍ",
      "translation": {
        "en": "Ja'far",
        "ur": "جعفر",
        "tr": "Ca'fer",
        "fa": "جعفر",
        "id": "Ja'far",
        "bn": "জাফর",
        "es": "Ja'far",
        "fr": "Ja'far",
        "de": "Ja'far",
        "ru": "Джафар",
        "zh": "贾法尔"
      },
      "pos": "N"
    },
    {
      "word": "عَلَيْهِمَا",
      "translation": {
        "en": "upon them both",
        "ur": "ان دونوں پر",
        "tr": "ikisine de",
        "fa": "بر هر دوی آنها",
        "id": "atas keduanya",
        "bn": "তাঁদের উভয়ের উপর",
        "es": "sobre ambos",
        "fr": "sur eux deux",
        "de": "auf ihnen beiden",
        "ru": "на них обоих",
        "zh": "在他们二位之上"
      },
      "pos": "PREP"
    },
    {
      "word": "السَّلَامُ",
      "translation": {
        "en": "peace",
        "ur": "سلام",
        "tr": "selâm",
        "fa": "سلام",
        "id": "salam/kedamaian",
        "bn": "শান্তি",
        "es": "la paz",
        "fr": "la paix",
        "de": "der Friede",
        "ru": "мир",
        "zh": "平安"
      },
      "pos": "N"
    },
    {
      "word": "قَالَ",
      "translation": {
        "en": "he said",
        "ur": "فرمایا",
        "tr": "buyurdu",
        "fa": "فرمود",
        "id": "bersabda",
        "bn": "বলেছেন",
        "es": "dijo",
        "fr": "il a dit",
        "de": "er sagte",
        "ru": "он сказал",
        "zh": "他说"
      },
      "pos": "V"
    }
  ],
  "translations": {
    "en": "Muhammad ibn al-Hasan narrated to us. He said: Ahmad ibn Idris narrated to us, from Muhammad ibn Ahmad, from Ali ibn Ismail, from Muhammad ibn Amr al-Zayyat, from Fa'id al-Hannat, from Abu al-Hasan Musa ibn Ja'far (peace be upon them both). He said:",
    "ur": "محمد بن الحسن نے ہم سے بیان کیا، کہا: احمد بن ادریس نے ہم سے بیان کیا، محمد بن احمد سے، علی بن اسماعیل سے، محمد بن عمرو الزیات سے، فائد الحناط سے، ابو الحسن موسیٰ بن جعفر (علیہما السلام) سے، آپ نے فرمایا:",
    "tr": "Muhammed bin el-Hasen bize rivayet etti. Dedi ki: Ahmed bin İdris bize rivayet etti, Muhammed bin Ahmed'den, Ali bin İsmail'den, Muhammed bin Amr ez-Zeyyât'tan, Fâid el-Hannât'tan, Ebu'l-Hasen Mûsâ bin Ca'fer'den (aleyhimesselâm). Buyurdu ki:",
    "fa": "محمد بن الحسن برای ما روایت کرد، گفت: احمد بن ادریس برای ما روایت کرد، از محمد بن احمد، از علی بن اسماعیل، از محمد بن عمرو الزیات، از فائد الحناط، از ابوالحسن موسی بن جعفر (علیهما السلام)، فرمود:",
    "id": "Muhammad bin al-Hasan menceritakan kepada kami. Ia berkata: Ahmad bin Idris menceritakan kepada kami, dari Muhammad bin Ahmad, dari Ali bin Ismail, dari Muhammad bin Amr al-Zayyat, dari Fa'id al-Hannat, dari Abu al-Hasan Musa bin Ja'far (alaihimas salam). Beliau bersabda:",
    "bn": "মুহাম্মাদ ইবনে আল-হাসান আমাদের বর্ণনা করেছেন। তিনি বলেছেন: আহমাদ ইবনে ইদরিস আমাদের বর্ণনা করেছেন, মুহাম্মাদ ইবনে আহমাদ থেকে, আলী ইবনে ইসমাইল থেকে, মুহাম্মাদ ইবনে আমর আল-যাইয়াত থেকে, ফায়িদ আল-হান্নাত থেকে, আবুল হাসান মূসা ইবনে জাফর (আলাইহিমাস সালাম) থেকে। তিনি বলেছেন:",
    "es": "Muhammad ibn al-Hasan nos narró. Dijo: Ahmad ibn Idris nos narró, de Muhammad ibn Ahmad, de Ali ibn Ismail, de Muhammad ibn Amr al-Zayyat, de Fa'id al-Hannat, de Abu al-Hasan Musa ibn Ja'far (la paz sea con ambos). Dijo:",
    "fr": "Muhammad ibn al-Hasan nous a raconté. Il a dit : Ahmad ibn Idris nous a raconté, d'après Muhammad ibn Ahmad, d'après Ali ibn Ismaïl, d'après Muhammad ibn Amr al-Zayyât, d'après Fâ'id al-Hannât, d'après Abou al-Hasan Moûsâ ibn Ja'far (que la paix soit sur eux deux). Il a dit :",
    "de": "Muhammad ibn al-Hasan berichtete uns. Er sagte: Ahmad ibn Idris berichtete uns, von Muhammad ibn Ahmad, von Ali ibn Ismail, von Muhammad ibn Amr al-Zayyat, von Fa'id al-Hannat, von Abu al-Hasan Musa ibn Ja'far (Friede sei auf ihnen beiden). Er sagte:",
    "ru": "Мухаммад ибн аль-Хасан рассказал нам. Он сказал: Ахмад ибн Идрис рассказал нам, от Мухаммада ибн Ахмада, от Али ибн Исмаила, от Мухаммада ибн Амра аз-Заййата, от Фаида аль-Ханната, от Абу аль-Хасана Мусы ибн Джафара (мир им обоим). Он сказал:",
    "zh": "穆罕默德·本·哈桑为我们讲述道，他说：艾哈迈德·本·伊德里斯为我们讲述，来自穆罕默德·本·艾哈迈德，来自阿里·本·伊斯玛仪，来自穆罕默德·本·阿姆尔·扎亚特，来自法伊德·汉纳特，来自阿布·哈桑·穆萨·本·贾法尔（愿二位平安）。他说："
  }
}