{
  "word_analysis": [
    {
      "word": "مَا",
      "translation": {
        "en": "not/never",
        "ur": "نہیں",
        "tr": "hiç/değil",
        "fa": "هیچ/نه",
        "id": "tidak pernah",
        "bn": "না/কখনো না",
        "es": "no/nunca",
        "fr": "ne/jamais",
        "de": "nicht/niemals",
        "ru": "не/никогда",
        "zh": "不/从不"
      },
      "pos": "NEG"
    },
    {
      "word": "أَحْسَنَ",
      "translation": {
        "en": "gave generously",
        "ur": "احسان کیا",
        "tr": "ihsan etti",
        "fa": "نیکو انجام داد",
        "id": "berbuat baik",
        "bn": "ভালোভাবে দিল",
        "es": "dio bien",
        "fr": "donna bien",
        "de": "gut spendete",
        "ru": "хорошо подал",
        "zh": "好好地给予"
      },
      "pos": "V"
    },
    {
      "word": "عَبْدٌ",
      "translation": {
        "en": "a servant",
        "ur": "ایک بندہ",
        "tr": "bir kul",
        "fa": "بنده‌ای",
        "id": "seorang hamba",
        "bn": "একজন বান্দা",
        "es": "un siervo",
        "fr": "un serviteur",
        "de": "ein Diener",
        "ru": "раб/слуга",
        "zh": "一个仆人"
      },
      "pos": "N"
    },
    {
      "word": "الصَّدَقَةَ",
      "translation": {
        "en": "charity",
        "ur": "صدقہ",
        "tr": "sadaka",
        "fa": "صدقه",
        "id": "sedekah",
        "bn": "সদকা",
        "es": "limosna/caridad",
        "fr": "aumône",
        "de": "Almosen/Sadaqa",
        "ru": "садака/милостыня",
        "zh": "施舍/慈善"
      },
      "pos": "N"
    },
    {
      "word": "فِي",
      "translation": {
        "en": "in",
        "ur": "میں",
        "tr": "-de/-da",
        "fa": "در",
        "id": "di dalam",
        "bn": "মধ্যে",
        "es": "en",
        "fr": "dans",
        "de": "in",
        "ru": "в",
        "zh": "在"
      },
      "pos": "PREP"
    },
    {
      "word": "الدُّنْيَا",
      "translation": {
        "en": "this world",
        "ur": "دنیا",
        "tr": "bu dünya",
        "fa": "دنیا",
        "id": "dunia",
        "bn": "দুনিয়া",
        "es": "este mundo",
        "fr": "ce monde",
        "de": "dieser Welt",
        "ru": "этом мире",
        "zh": "今世"
      },
      "pos": "N"
    },
    {
      "word": "إِلَّا",
      "translation": {
        "en": "except",
        "ur": "مگر/سوائے",
        "tr": "ancak/mutlaka",
        "fa": "مگر/جز",
        "id": "kecuali",
        "bn": "ছাড়া/কিন্তু",
        "es": "sino",
        "fr": "que",
        "de": "außer dass",
        "ru": "не иначе как",
        "zh": "除非"
      },
      "pos": "PART"
    },
    {
      "word": "أَحْسَنَ",
      "translation": {
        "en": "improves/betters",
        "ur": "بہتر کرتا ہے",
        "tr": "iyileştirir",
        "fa": "نیکو می‌کند",
        "id": "memperbaiki",
        "bn": "ভালো করেন",
        "es": "mejora",
        "fr": "améliore",
        "de": "verbessert",
        "ru": "улучшает",
        "zh": "改善"
      },
      "pos": "V"
    },
    {
      "word": "اللَّهُ",
      "translation": {
        "en": "God",
        "ur": "اللہ",
        "tr": "Allah",
        "fa": "خدا",
        "id": "Allah",
        "bn": "আল্লাহ",
        "es": "Dios/Allah",
        "fr": "Dieu/Allah",
        "de": "Gott/Allah",
        "ru": "Аллах",
        "zh": "安拉/真主"
      },
      "pos": "N"
    },
    {
      "word": "الْخِلَافَةَ",
      "translation": {
        "en": "the succession/stewardship",
        "ur": "خلافت/نگہبانی",
        "tr": "halifeliği/bakımı",
        "fa": "جانشینی/سرپرستی",
        "id": "kepengurusan/penerusan",
        "bn": "উত্তরাধিকার/তত্ত্বাবধান",
        "es": "la sucesión/custodia",
        "fr": "la succession/tutelle",
        "de": "die Nachfolge/Fürsorge",
        "ru": "преемство/попечение",
        "zh": "后嗣/照管"
      },
      "pos": "N"
    },
    {
      "word": "عَلَى",
      "translation": {
        "en": "over/upon",
        "ur": "پر",
        "tr": "üzerinde",
        "fa": "بر",
        "id": "atas",
        "bn": "উপর",
        "es": "sobre",
        "fr": "sur",
        "de": "über",
        "ru": "над",
        "zh": "对…的"
      },
      "pos": "PREP"
    },
    {
      "word": "وُلْدِهِ",
      "translation": {
        "en": "his children",
        "ur": "اس کی اولاد",
        "tr": "çocukları",
        "fa": "فرزندانش",
        "id": "anak-anaknya",
        "bn": "তার সন্তানদের",
        "es": "sus hijos",
        "fr": "ses enfants",
        "de": "seine Kinder",
        "ru": "его детей",
        "zh": "他的子嗣"
      },
      "pos": "N"
    },
    {
      "word": "مِنْ",
      "translation": {
        "en": "from/after",
        "ur": "سے",
        "tr": "-den",
        "fa": "از",
        "id": "dari",
        "bn": "থেকে",
        "es": "desde",
        "fr": "depuis",
        "de": "von/nach",
        "ru": "после",
        "zh": "在…之后"
      },
      "pos": "PREP"
    },
    {
      "word": "بَعْدِهِ",
      "translation": {
        "en": "after him",
        "ur": "اس کے بعد",
        "tr": "ondan sonra",
        "fa": "پس از او",
        "id": "setelahnya",
        "bn": "তার পরে",
        "es": "después de él",
        "fr": "après lui",
        "de": "nach ihm",
        "ru": "после него",
        "zh": "他之后"
      },
      "pos": "N"
    }
  ],
  "translations": {
    "en": "'No servant gives good charity in this world except that God betters the succession over his children after him.'",
    "ur": "'کوئی بندہ دنیا میں صدقہ اچھے طریقے سے نہیں دیتا مگر یہ کہ اللہ اس کی اولاد پر اس کے بعد خلافت (نگہداشت) کو اچھا کر دیتا ہے۔'",
    "tr": "'Hiçbir kul dünyada güzelce sadaka vermez ki Allah, onun çocuklarına ondan sonra olan halifeliği (bakımı) güzelleştirmesin.'",
    "fa": "'هیچ بنده‌ای در دنیا صدقه را به نیکویی نمی‌دهد مگر آنکه خداوند جانشینی (سرپرستی) بر فرزندانش پس از او را نیکو می‌کند.'",
    "id": "'Tidaklah seorang hamba memberi sedekah dengan baik di dunia kecuali Allah memperbaiki kepengurusan atas anak-anaknya setelahnya.'",
    "bn": "'কোনো বান্দা দুনিয়ায় ভালোভাবে সদকা দেয় না, কিন্তু আল্লাহ তার সন্তানদের উপর তার পরে উত্তম তত্ত্বাবধান করেন।'",
    "es": "'Ningún siervo da bien la limosna en este mundo sin que Dios mejore la sucesión sobre sus hijos después de él.'",
    "fr": "'Aucun serviteur ne donne bien l'aumône en ce monde sans que Dieu n'améliore la succession sur ses enfants après lui.'",
    "de": "'Kein Diener gibt in dieser Welt gut Almosen, ohne dass Gott die Nachfolge über seine Kinder nach ihm verbessert.'",
    "ru": "'Ни один раб не подаёт хорошей милостыни в этом мире, чтобы Аллах не улучшил преемство над его детьми после него.'",
    "zh": "'任何仆人在今世善于施舍，安拉必定在他之后善待其子嗣的继承。'"
  }
}