{
  "word_analysis": [
    {
      "word": "عَنْهُ",
      "translation": {
        "en": "from him",
        "ur": "اس سے",
        "tr": "ondan",
        "fa": "از او",
        "id": "darinya",
        "bn": "তাঁর থেকে",
        "es": "de él",
        "fr": "de lui",
        "de": "von ihm",
        "ru": "от него",
        "zh": "从他"
      },
      "pos": "PREP"
    },
    {
      "word": "عَنْ",
      "translation": {
        "en": "from",
        "ur": "سے",
        "tr": "-den",
        "fa": "از",
        "id": "dari",
        "bn": "থেকে",
        "es": "de",
        "fr": "de",
        "de": "von",
        "ru": "от",
        "zh": "从"
      },
      "pos": "PREP"
    },
    {
      "word": "عَلِيِّ",
      "translation": {
        "en": "Ali",
        "ur": "علی",
        "tr": "Ali",
        "fa": "علی",
        "id": "Ali",
        "bn": "আলী",
        "es": "Ali",
        "fr": "Ali",
        "de": "Ali",
        "ru": "Али",
        "zh": "阿里"
      },
      "pos": "N"
    },
    {
      "word": "بْنِ",
      "translation": {
        "en": "son of",
        "ur": "بن",
        "tr": "bin/oğlu",
        "fa": "بن",
        "id": "bin/putra",
        "bn": "ইবনে",
        "es": "hijo de",
        "fr": "fils de",
        "de": "Sohn von",
        "ru": "ибн/сын",
        "zh": "之子"
      },
      "pos": "N"
    },
    {
      "word": "مَعْبَدٍ",
      "translation": {
        "en": "Ma'bad",
        "ur": "معبد",
        "tr": "Ma'bed",
        "fa": "معبد",
        "id": "Ma'bad",
        "bn": "মা'বাদ",
        "es": "Ma'bad",
        "fr": "Ma'bad",
        "de": "Ma'bad",
        "ru": "Ма'бад",
        "zh": "马阿巴德"
      },
      "pos": "N"
    },
    {
      "word": "عَنْ",
      "translation": {
        "en": "from",
        "ur": "سے",
        "tr": "-den",
        "fa": "از",
        "id": "dari",
        "bn": "থেকে",
        "es": "de",
        "fr": "de",
        "de": "von",
        "ru": "от",
        "zh": "从"
      },
      "pos": "PREP"
    },
    {
      "word": "عَبْدِ",
      "translation": {
        "en": "servant of",
        "ur": "بندہ",
        "tr": "kulu",
        "fa": "بنده",
        "id": "hamba",
        "bn": "বান্দা",
        "es": "siervo de",
        "fr": "serviteur de",
        "de": "Diener von",
        "ru": "раб",
        "zh": "仆人"
      },
      "pos": "N"
    },
    {
      "word": "اللَّهِ",
      "translation": {
        "en": "God",
        "ur": "اللہ",
        "tr": "Allah",
        "fa": "الله",
        "id": "Allah",
        "bn": "আল্লাহ",
        "es": "Dios/Allah",
        "fr": "Dieu/Allah",
        "de": "Gott/Allah",
        "ru": "Аллах",
        "zh": "安拉/真主"
      },
      "pos": "N"
    },
    {
      "word": "بْنِ",
      "translation": {
        "en": "son of",
        "ur": "بن",
        "tr": "bin/oğlu",
        "fa": "بن",
        "id": "bin/putra",
        "bn": "ইবনে",
        "es": "hijo de",
        "fr": "fils de",
        "de": "Sohn von",
        "ru": "ибн/сын",
        "zh": "之子"
      },
      "pos": "N"
    },
    {
      "word": "الْقَاسِمِ",
      "translation": {
        "en": "al-Qasim",
        "ur": "القاسم",
        "tr": "el-Kasım",
        "fa": "القاسم",
        "id": "al-Qasim",
        "bn": "আল-কাসিম",
        "es": "al-Qasim",
        "fr": "al-Qasim",
        "de": "al-Qasim",
        "ru": "аль-Касим",
        "zh": "阿尔-卡西姆"
      },
      "pos": "N"
    },
    {
      "word": "عَنْ",
      "translation": {
        "en": "from",
        "ur": "سے",
        "tr": "-den",
        "fa": "از",
        "id": "dari",
        "bn": "থেকে",
        "es": "de",
        "fr": "de",
        "de": "von",
        "ru": "от",
        "zh": "从"
      },
      "pos": "PREP"
    },
    {
      "word": "عَبْدِ",
      "translation": {
        "en": "servant of",
        "ur": "بندہ",
        "tr": "kulu",
        "fa": "بنده",
        "id": "hamba",
        "bn": "বান্দা",
        "es": "siervo de",
        "fr": "serviteur de",
        "de": "Diener von",
        "ru": "раб",
        "zh": "仆人"
      },
      "pos": "N"
    },
    {
      "word": "اللَّهِ",
      "translation": {
        "en": "God",
        "ur": "اللہ",
        "tr": "Allah",
        "fa": "الله",
        "id": "Allah",
        "bn": "আল্লাহ",
        "es": "Dios/Allah",
        "fr": "Dieu/Allah",
        "de": "Gott/Allah",
        "ru": "Аллах",
        "zh": "安拉/真主"
      },
      "pos": "N"
    },
    {
      "word": "بْنِ",
      "translation": {
        "en": "son of",
        "ur": "بن",
        "tr": "bin/oğlu",
        "fa": "بن",
        "id": "bin/putra",
        "bn": "ইবনে",
        "es": "hijo de",
        "fr": "fils de",
        "de": "Sohn von",
        "ru": "ибн/сын",
        "zh": "之子"
      },
      "pos": "N"
    },
    {
      "word": "سِنَانٍ",
      "translation": {
        "en": "Sinan",
        "ur": "سنان",
        "tr": "Sinan",
        "fa": "سنان",
        "id": "Sinan",
        "bn": "সিনান",
        "es": "Sinan",
        "fr": "Sinan",
        "de": "Sinan",
        "ru": "Синан",
        "zh": "西南"
      },
      "pos": "N"
    },
    {
      "word": "عَنْ",
      "translation": {
        "en": "from",
        "ur": "سے",
        "tr": "-den",
        "fa": "از",
        "id": "dari",
        "bn": "থেকে",
        "es": "de",
        "fr": "de",
        "de": "von",
        "ru": "от",
        "zh": "从"
      },
      "pos": "PREP"
    },
    {
      "word": "أَبِي",
      "translation": {
        "en": "Abu (father of)",
        "ur": "ابو (والد)",
        "tr": "Ebu (babası)",
        "fa": "ابو (پدر)",
        "id": "Abu (ayah dari)",
        "bn": "আবু (পিতা)",
        "es": "Abu (padre de)",
        "fr": "Abu (père de)",
        "de": "Abu (Vater von)",
        "ru": "Абу (отец)",
        "zh": "阿布（之父）"
      },
      "pos": "N"
    },
    {
      "word": "عَبْدِ",
      "translation": {
        "en": "servant of",
        "ur": "بندہ",
        "tr": "kulu",
        "fa": "بنده",
        "id": "hamba",
        "bn": "বান্দা",
        "es": "siervo de",
        "fr": "serviteur de",
        "de": "Diener von",
        "ru": "раб",
        "zh": "仆人"
      },
      "pos": "N"
    },
    {
      "word": "اللَّهِ",
      "translation": {
        "en": "God",
        "ur": "اللہ",
        "tr": "Allah",
        "fa": "الله",
        "id": "Allah",
        "bn": "আল্লাহ",
        "es": "Dios/Allah",
        "fr": "Dieu/Allah",
        "de": "Gott/Allah",
        "ru": "Аллах",
        "zh": "安拉/真主"
      },
      "pos": "N"
    },
    {
      "word": "عَلَيْهِ",
      "translation": {
        "en": "upon him",
        "ur": "اس پر",
        "tr": "ona",
        "fa": "بر او",
        "id": "atasnya",
        "bn": "তাঁর উপর",
        "es": "sobre él",
        "fr": "sur lui",
        "de": "auf ihm",
        "ru": "на нём",
        "zh": "在他之上"
      },
      "pos": "PREP"
    },
    {
      "word": "السَّلَامُ",
      "translation": {
        "en": "peace",
        "ur": "سلام",
        "tr": "selam",
        "fa": "سلام",
        "id": "salam/kedamaian",
        "bn": "শান্তি",
        "es": "paz",
        "fr": "paix",
        "de": "Friede",
        "ru": "мир",
        "zh": "平安"
      },
      "pos": "N"
    },
    {
      "word": "قَالَ",
      "translation": {
        "en": "he said",
        "ur": "فرمایا",
        "tr": "buyurdu",
        "fa": "فرمود",
        "id": "bersabda",
        "bn": "বলেছেন",
        "es": "dijo",
        "fr": "a dit",
        "de": "sagte",
        "ru": "сказал",
        "zh": "他说"
      },
      "pos": "V"
    }
  ],
  "translations": {
    "en": "From him, from Ali ibn Ma'bad, from Abdullah ibn al-Qasim, from Abdullah ibn Sinan, from Abu Abdillah (peace be upon him) who said:",
    "ur": "اس سے، علی بن معبد سے، عبداللہ بن القاسم سے، عبداللہ بن سنان سے، ابو عبداللہ علیہ السلام سے روایت ہے کہ آپ نے فرمایا:",
    "tr": "Ondan, Ali b. Ma'bed'den, Abdullah b. el-Kasım'dan, Abdullah b. Sinan'dan, Ebu Abdullah (a.s.)'dan şöyle rivayet edilmiştir:",
    "fa": "از او، از علی بن معبد، از عبدالله بن القاسم، از عبدالله بن سنان، از ابوعبدالله علیه السلام روایت شده که فرمود:",
    "id": "Dari dia, dari Ali bin Ma'bad, dari Abdullah bin al-Qasim, dari Abdullah bin Sinan, dari Abu Abdillah (alaihis salam) yang bersabda:",
    "bn": "তাঁর থেকে, আলী ইবনে মা'বাদ থেকে, আবদুল্লাহ ইবনে আল-কাসিম থেকে, আবদুল্লাহ ইবনে সিনান থেকে, আবু আবদিল্লাহ আলাইহিস সালাম থেকে বর্ণিত, তিনি বলেছেন:",
    "es": "De él, de Ali ibn Ma'bad, de Abdullah ibn al-Qasim, de Abdullah ibn Sinan, de Abu Abdillah (paz sea con él) quien dijo:",
    "fr": "De lui, d'Ali ibn Ma'bad, d'Abdullah ibn al-Qasim, d'Abdullah ibn Sinan, d'Abu Abdillah (que la paix soit sur lui) qui a dit :",
    "de": "Von ihm, von Ali ibn Ma'bad, von Abdullah ibn al-Qasim, von Abdullah ibn Sinan, von Abu Abdillah (Friede sei mit ihm), der sagte:",
    "ru": "От него, от Али ибн Ма'бада, от Абдуллаха ибн аль-Касима, от Абдуллаха ибн Синана, от Абу Абдиллаха (мир ему), который сказал:",
    "zh": "从他，从阿里·本·马阿巴德，从阿卜杜拉·本·卡西姆，从阿卜杜拉·本·西南，从阿布·阿卜杜拉（愿主赐他平安）传述，他说："
  }
}